Workbook

Sheet Executive Summary
A1: EXECUTIVE SUMMARY - 36-MONTH PROJECTION
A3: Metric | B3: Y1M1 | C3: Y1M2 | D3: Y1M3 | E3: Y1M4 | F3: Y1M5 | G3: Y1M6 | H3: Y1M7 | I3: Y1M8 | J3: Y1M9 | K3: Y1M10 | L3: Y1M11 | M3: Y1M12 | N3: Y2M1 | O3: Y2M2 | P3: Y2M3 | Q3: Y2M4 | R3: Y2M5 | S3: Y2M6 | T3: Y2M7 | U3: Y2M8 | V3: Y2M9 | W3: Y2M10 | X3: Y2M11 | Y3: Y2M12 | Z3: Y3M1 | AA3: Y3M2 | AB3: Y3M3 | AC3: Y3M4 | AD3: Y3M5 | AE3: Y3M6 | AF3: Y3M7 | AG3: Y3M8 | AH3: Y3M9 | AI3: Y3M10 | AJ3: Y3M11 | AK3: Y3M12
A4: SEAT AND ACCOUNT GROWTH
A5: New Seats | B5: ='Revenue Model'!B$27 -> 0 | C5: ='Revenue Model'!C$27 -> 0 | D5: ='Revenue Model'!D$27 -> 0 | E5: ='Revenue Model'!E$27 -> 242 | F5: ='Revenue Model'!F$27 -> 145 | G5: ='Revenue Model'!G$27 -> 218 | H5: ='Revenue Model'!H$27 -> 266 | I5: ='Revenue Model'!I$27 -> 266 | ... AK5: ='Revenue Model'!AK$27 -> 1505
A6: Active Seats (EOP) | B6: ='Revenue Model'!B$28 -> 0 | C6: ='Revenue Model'!C$28 -> 0 | D6: ='Revenue Model'!D$28 -> 0 | E6: ='Revenue Model'!E$28 -> 242 | F6: ='Revenue Model'!F$28 -> 386 | G6: ='Revenue Model'!G$28 -> 602 | H6: ='Revenue Model'!H$28 -> 866 | I6: ='Revenue Model'!I$28 -> 1129 | ... AK6: ='Revenue Model'!AK$28 -> 23091
A8: REVENUE
A9: MRR | B9: ='Revenue Model'!B$31 -> 0 | C9: ='Revenue Model'!C$31 -> 0 | D9: ='Revenue Model'!D$31 -> 0 | E9: ='Revenue Model'!E$31 -> 7150 | F9: ='Revenue Model'!F$31 -> 10709.503 | G9: ='Revenue Model'!G$31 -> 17899.835 | H9: ='Revenue Model'!H$31 -> 25452.586 | I9: ='Revenue Model'!I$31 -> 33182.414 | ... AK9: ='Revenue Model'!AK$31 -> 716489.77
A10: ARR (MRR x 12) | B10: ='Revenue Model'!B$32 -> 0 | C10: ='Revenue Model'!C$32 -> 0 | D10: ='Revenue Model'!D$32 -> 0 | E10: ='Revenue Model'!E$32 -> 85800 | F10: ='Revenue Model'!F$32 -> 128514.04 | G10: ='Revenue Model'!G$32 -> 214798.02 | H10: ='Revenue Model'!H$32 -> 305431.04 | I10: ='Revenue Model'!I$32 -> 398188.96 | ... AK10: ='Revenue Model'!AK$32 -> 8597877.2
A11: UNIT ECONOMICS
A12: Total COGS | B12: ='COGS Analysis'!B$20 -> 0 | C12: ='COGS Analysis'!C$20 -> 0 | D12: ='COGS Analysis'!D$20 -> 0 | E12: ='COGS Analysis'!E$20 -> 3193.93 | F12: ='COGS Analysis'!F$20 -> 3943.7156 | G12: ='COGS Analysis'!G$20 -> 5122.0752 | H12: ='COGS Analysis'!H$20 -> 6526.465 | I12: ='COGS Analysis'!I$20 -> 7931.5 | ... AK12: ='COGS Analysis'!AK$20 -> 88735.079
A13: Gross Margin % | B13: ='COGS Analysis'!B$23 -> 0 | C13: ='COGS Analysis'!C$23 -> 0 | D13: ='COGS Analysis'!D$23 -> 0 | E13: ='COGS Analysis'!E$23 -> 0.5532965 | F13: ='COGS Analysis'!F$23 -> 0.63175551 | G13: ='COGS Analysis'!G$23 -> 0.71384791 | H13: ='COGS Analysis'!H$23 -> 0.74358343 | I13: ='COGS Analysis'!I$23 -> 0.76097278 | ... AK13: ='COGS Analysis'!AK$23 -> 0.87615304
A14: PROFITABILITY
A15: EBITDA | B15: ='P&L Statement'!B$17 -> -68375 | C15: ='P&L Statement'!C$17 -> -62375 | D15: ='P&L Statement'!D$17 -> -62375 | E15: ='P&L Statement'!E$17 -> -87246.571 | F15: ='P&L Statement'!F$17 -> -83023.745 | G15: ='P&L Statement'!G$17 -> -81708.146 | H15: ='P&L Statement'!H$17 -> -75528.089 | I15: ='P&L Statement'!I$17 -> -78203.297 | ... AK15: ='P&L Statement'!AK$17 -> 232639.15
A16: EBITDA Margin % | B16: ='P&L Statement'!B$18 -> 0 | C16: ='P&L Statement'!C$18 -> 0 | D16: ='P&L Statement'!D$18 -> 0 | E16: ='P&L Statement'!E$18 -> -12.202318 | F16: ='P&L Statement'!F$18 -> -7.7523431 | G16: ='P&L Statement'!G$18 -> -4.564743 | H16: ='P&L Statement'!H$18 -> -2.9674033 | I16: ='P&L Statement'!I$18 -> -2.3567694 | ... AK16: ='P&L Statement'!AK$18 -> 0.32469291
A17: Headcount | B17: ='Staffing Plan'!F$33 -> 3 | C17: ='Staffing Plan'!G$33 -> 3 | D17: ='Staffing Plan'!H$33 -> 3 | E17: ='Staffing Plan'!I$33 -> 5 | F17: ='Staffing Plan'!J$33 -> 5 | G17: ='Staffing Plan'!K$33 -> 5 | H17: ='Staffing Plan'!L$33 -> 5 | I17: ='Staffing Plan'!M$33 -> 6 | ... AK17: ='Staffing Plan'!AO$33 -> 23
A19: ANNUAL SUMMARY
A20: Metric | B20: Year 1 | C20: Year 2 | D20: Year 3
A21: Ending ARR | B21: =M$9*12 -> 791761.09 | C21: =Y$9*12 -> 3310491.9 | D21: =AK$9*12 -> 8597877.2
A22: Ending Seats | B22: =M$6 -> 2247 | C22: =Y$6 -> 9022 | D22: =AK$6 -> 23091
A23: Gross Margin % | B23: ='COGS Analysis'!M$23 -> 0.78929322 | C23: ='COGS Analysis'!Y$23 -> 0.84102069 | D23: ='COGS Analysis'!AK$23 -> 0.87615304
A24: Ending EBITDA | B24: ='P&L Statement'!M$17 -> -64930.513 | C24: ='P&L Statement'!Y$17 -> -1698.3864 | D24: ='P&L Statement'!AK$17 -> 232639.15
A25: EBITDA Margin % | B25: ='P&L Statement'!M$18 -> -0.98409251 | C25: ='P&L Statement'!Y$18 -> -0.006156377 | D25: ='P&L Statement'!AK$18 -> 0.32469291
A26: Ending Headcount | B26: =M$17 -> 7 | C26: =Y$17 -> 13 | D26: =AK$17 -> 23
A27: New Accounts (Year) | B27: ='Revenue Model'!M$35 -> 238 | C27: ='Revenue Model'!Y$35-'Revenue Model'!M$35 -> 452 | D27: ='Revenue Model'!AK$35-'Revenue Model'!Y$35 -> 627
A28: YoY ARR Growth % | B28: N/A | C28: =(Y$9*12-M$9*12)/(M$9*12) -> 3.1811753 | D28: =(AK$9*12-Y$9*12)/(Y$9*12) -> 1.59716
A30: CASH & RUNWAY
A31: Seed Funding | B31: ='Model Inputs'!B83 -> 2500000 | C31: Runway (Months) | D31: ='P&L Statement'!B22 -> 36 | E31: Ending Cash | F31: ='P&L Statement'!AK21 -> 2266615
A33: Month | B33: M1 | C33: M2 | D33: M3 | E33: M4 | F33: M5 | G33: M6 | H33: M7 | I33: M8 | J33: M9 | K33: M10 | L33: M11 | M33: M12 | N33: M13 | O33: M14 | P33: M15 | Q33: M16 | R33: M17 | S33: M18 | T33: M19 | U33: M20 | V33: M21 | W33: M22 | X33: M23 | Y33: M24 | Z33: M25 | AA33: M26 | AB33: M27 | AC33: M28 | AD33: M29 | AE33: M30 | AF33: M31 | AG33: M32 | AH33: M33 | AI33: M34 | AJ33: M35 | AK33: M36
A34: Monthly EBITDA | B34: ='P&L Statement'!B17 -> -68375 | C34: ='P&L Statement'!C17 -> -62375 | D34: ='P&L Statement'!D17 -> -62375 | E34: ='P&L Statement'!E17 -> -87246.571 | F34: ='P&L Statement'!F17 -> -83023.745 | G34: ='P&L Statement'!G17 -> -81708.146 | H34: ='P&L Statement'!H17 -> -75528.089 | I34: ='P&L Statement'!I17 -> -78203.297 | ... AK34: ='P&L Statement'!AK17 -> 232639.15
A35: Cumulative EBITDA | B35: ='P&L Statement'!B20 -> -68375 | C35: ='P&L Statement'!C20 -> -130750 | D35: ='P&L Statement'!D20 -> -193125 | E35: ='P&L Statement'!E20 -> -280371.57 | F35: ='P&L Statement'!F20 -> -363395.32 | G35: ='P&L Statement'!G20 -> -445103.46 | H35: ='P&L Statement'!H20 -> -520631.55 | I35: ='P&L Statement'!I20 -> -598834.85 | ... AK35: ='P&L Statement'!AK20 -> -233385.05
A36: Cash Position | B36: ='P&L Statement'!B21 -> 2431625 | C36: ='P&L Statement'!C21 -> 2369250 | D36: ='P&L Statement'!D21 -> 2306875 | E36: ='P&L Statement'!E21 -> 2219628.4 | F36: ='P&L Statement'!F21 -> 2136604.7 | G36: ='P&L Statement'!G21 -> 2054896.5 | H36: ='P&L Statement'!H21 -> 1979368.4 | I36: ='P&L Statement'!I21 -> 1901165.2 | ... AK36: ='P&L Statement'!AK21 -> 2266615
A37: Status | B37: =IF(B36>500000,"OK",IF(B36>250000,"Watch",IF(B36>0,"Low","OUT"))) -> OK | C37: =IF(C36>500000,"OK",IF(C36>250000,"Watch",IF(C36>0,"Low","OUT"))) -> OK | D37: =IF(D36>500000,"OK",IF(D36>250000,"Watch",IF(D36>0,"Low","OUT"))) -> OK | E37: =IF(E36>500000,"OK",IF(E36>250000,"Watch",IF(E36>0,"Low","OUT"))) -> OK | F37: =IF(F36>500000,"OK",IF(F36>250000,"Watch",IF(F36>0,"Low","OUT"))) -> OK | G37: =IF(G36>500000,"OK",IF(G36>250000,"Watch",IF(G36>0,"Low","OUT"))) -> OK | H37: =IF(H36>500000,"OK",IF(H36>250000,"Watch",IF(H36>0,"Low","OUT"))) -> OK | I37: =IF(I36>500000,"OK",IF(I36>250000,"Watch",IF(I36>0,"Low","OUT"))) -> OK | ... AK37: =IF(AK36>500000,"OK",IF(AK36>250000,"Watch",IF(AK36>0,"Low","OUT"))) -> OK
A39: YEAR-END SUMMARY | B39: Y1 (M12) | C39: Y2 (M24) | D39: Y3 (M36)
A40: Year-End Cash | B40: ='P&L Statement'!M21 -> 1619778.4 | C40: ='P&L Statement'!Y21 -> 1014396.4 | D40: ='P&L Statement'!AK21 -> 2266615
A41: Year Cash Burn | B41: =SUM('P&L Statement'!B17:M17) -> -880221.57 | C41: =SUM('P&L Statement'!N17:Y17) -> -605382.01 | D41: =SUM('P&L Statement'!Z17:AK17) -> 1252218.5
A42: Year Low Point | B42: =MIN('P&L Statement'!B21:M21) -> 1619778.4 | C42: =MIN('P&L Statement'!N21:Y21) -> 1014396.4 | D42: =MIN('P&L Statement'!Z21:AK21) -> 999147.36

Sheet Revenue Model
A1: REVENUE MODEL - 36-MONTH BOTTOM-UP
A3: Metric | B3: Y1M1 | C3: Y1M2 | D3: Y1M3 | E3: Y1M4 | F3: Y1M5 | G3: Y1M6 | H3: Y1M7 | I3: Y1M8 | J3: Y1M9 | K3: Y1M10 | L3: Y1M11 | M3: Y1M12 | N3: Y2M1 | O3: Y2M2 | P3: Y2M3 | Q3: Y2M4 | R3: Y2M5 | S3: Y2M6 | T3: Y2M7 | U3: Y2M8 | V3: Y2M9 | W3: Y2M10 | X3: Y2M11 | Y3: Y2M12 | Z3: Y3M1 | AA3: Y3M2 | AB3: Y3M3 | AC3: Y3M4 | AD3: Y3M5 | AE3: Y3M6 | AF3: Y3M7 | AG3: Y3M8 | AH3: Y3M9 | AI3: Y3M10 | AJ3: Y3M11 | AK3: Y3M12
A4: SALES ACQUISITION (Verticals)
A5: Crypto/Web3 Accounts | B5: ='Model Inputs'!B192 -> 0 | C5: ='Model Inputs'!C192 -> 0 | D5: ='Model Inputs'!D192 -> 0 | E5: ='Model Inputs'!E192 -> 8 | F5: ='Model Inputs'!F192 -> 6 | G5: ='Model Inputs'!G192 -> 7 | H5: ='Model Inputs'!H192 -> 9 | I5: ='Model Inputs'!I192 -> 9 | ... AK5: ='Model Inputs'!AK192 -> 12
A6: Crypto/Web3 Seats | B6: =B5*'Model Inputs'!$B$116 -> 0 | C6: =C5*'Model Inputs'!$B$116 -> 0 | D6: =D5*'Model Inputs'!$B$116 -> 0 | E6: =E5*'Model Inputs'!$B$116 -> 176 | F6: =F5*'Model Inputs'!$B$116 -> 132 | G6: =G5*'Model Inputs'!$B$116 -> 154 | H6: =H5*'Model Inputs'!$B$116 -> 198 | I6: =I5*'Model Inputs'!$B$116 -> 198 | ... M6: =M5*'Model Inputs'!$B$116 -> 198 | N6: =N5*'Model Inputs'!$C$116 -> 175 | O6: =O5*'Model Inputs'!$C$116 -> 175 | P6: =P5*'Model Inputs'!$C$116 -> 175 | Q6: =Q5*'Model Inputs'!$C$116 -> 200 | R6: =R5*'Model Inputs'!$C$116 -> 225 | S6: =S5*'Model Inputs'!$C$116 -> 275 | T6: =T5*'Model Inputs'!$C$116 -> 300 | U6: =U5*'Model Inputs'!$C$116 -> 300 | ... Y6: =Y5*'Model Inputs'!$C$116 -> 375 | Z6: =Z5*'Model Inputs'!$D$116 -> 336 | AA6: =AA5*'Model Inputs'!$D$116 -> 336 | AB6: =AB5*'Model Inputs'!$D$116 -> 336 | AC6: =AC5*'Model Inputs'!$D$116 -> 336 | AD6: =AD5*'Model Inputs'!$D$116 -> 336 | AE6: =AE5*'Model Inputs'!$D$116 -> 336 | AF6: =AF5*'Model Inputs'!$D$116 -> 336 | AG6: =AG5*'Model Inputs'!$D$116 -> 336 | ... AL6: =AL5*'Model Inputs'!$D$116 -> 0
A7: Crypto Law Accounts | B7: ='Model Inputs'!B193 -> 0 | C7: ='Model Inputs'!C193 -> 0 | D7: ='Model Inputs'!D193 -> 0 | E7: ='Model Inputs'!E193 -> 1 | F7: ='Model Inputs'!F193 -> 0 | G7: ='Model Inputs'!G193 -> 1 | H7: ='Model Inputs'!H193 -> 1 | I7: ='Model Inputs'!I193 -> 1 | ... AK7: ='Model Inputs'!AK193 -> 2
A8: Crypto Law Seats | B8: =B7*'Model Inputs'!$B$117 -> 0 | C8: =C7*'Model Inputs'!$B$117 -> 0 | D8: =D7*'Model Inputs'!$B$117 -> 0 | E8: =E7*'Model Inputs'!$B$117 -> 44 | F8: =F7*'Model Inputs'!$B$117 -> 0 | G8: =G7*'Model Inputs'!$B$117 -> 44 | H8: =H7*'Model Inputs'!$B$117 -> 44 | I8: =I7*'Model Inputs'!$B$117 -> 44 | ... M8: =M7*'Model Inputs'!$B$117 -> 44 | N8: =N7*'Model Inputs'!$C$117 -> 50 | O8: =O7*'Model Inputs'!$C$117 -> 50 | P8: =P7*'Model Inputs'!$C$117 -> 50 | Q8: =Q7*'Model Inputs'!$C$117 -> 50 | R8: =R7*'Model Inputs'!$C$117 -> 50 | S8: =S7*'Model Inputs'!$C$117 -> 50 | T8: =T7*'Model Inputs'!$C$117 -> 50 | U8: =U7*'Model Inputs'!$C$117 -> 50 | ... Y8: =Y7*'Model Inputs'!$C$117 -> 100 | Z8: =Z7*'Model Inputs'!$D$117 -> 120 | AA8: =AA7*'Model Inputs'!$D$117 -> 120 | AB8: =AB7*'Model Inputs'!$D$117 -> 120 | AC8: =AC7*'Model Inputs'!$D$117 -> 120 | AD8: =AD7*'Model Inputs'!$D$117 -> 120 | AE8: =AE7*'Model Inputs'!$D$117 -> 120 | AF8: =AF7*'Model Inputs'!$D$117 -> 120 | AG8: =AG7*'Model Inputs'!$D$117 -> 120 | ... AL8: =AL7*'Model Inputs'!$D$117 -> 0
A9: Healthcare Accounts (Y2+) | B9: ='Model Inputs'!B194 -> 0 | C9: ='Model Inputs'!C194 -> 0 | D9: ='Model Inputs'!D194 -> 0 | E9: ='Model Inputs'!E194 -> 0 | F9: ='Model Inputs'!F194 -> 0 | G9: ='Model Inputs'!G194 -> 0 | H9: ='Model Inputs'!H194 -> 0 | I9: ='Model Inputs'!I194 -> 0 | ... AK9: ='Model Inputs'!AK194 -> 2
A10: Healthcare Seats | B10: =B9*'Model Inputs'!$B$118 -> 0 | C10: =C9*'Model Inputs'!$B$118 -> 0 | D10: =D9*'Model Inputs'!$B$118 -> 0 | E10: =E9*'Model Inputs'!$B$118 -> 0 | F10: =F9*'Model Inputs'!$B$118 -> 0 | G10: =G9*'Model Inputs'!$B$118 -> 0 | H10: =H9*'Model Inputs'!$B$118 -> 0 | I10: =I9*'Model Inputs'!$B$118 -> 0 | ... M10: =M9*'Model Inputs'!$B$118 -> 0 | N10: =N9*'Model Inputs'!$C$118 -> 15 | O10: =O9*'Model Inputs'!$C$118 -> 15 | P10: =P9*'Model Inputs'!$C$118 -> 15 | Q10: =Q9*'Model Inputs'!$C$118 -> 15 | R10: =R9*'Model Inputs'!$C$118 -> 15 | S10: =S9*'Model Inputs'!$C$118 -> 30 | T10: =T9*'Model Inputs'!$C$118 -> 30 | U10: =U9*'Model Inputs'!$C$118 -> 30 | ... Y10: =Y9*'Model Inputs'!$C$118 -> 30 | Z10: =Z9*'Model Inputs'!$D$118 -> 40 | AA10: =AA9*'Model Inputs'!$D$118 -> 40 | AB10: =AB9*'Model Inputs'!$D$118 -> 40 | AC10: =AC9*'Model Inputs'!$D$118 -> 40 | AD10: =AD9*'Model Inputs'!$D$118 -> 40 | AE10: =AE9*'Model Inputs'!$D$118 -> 40 | AF10: =AF9*'Model Inputs'!$D$118 -> 40 | AG10: =AG9*'Model Inputs'!$D$118 -> 40 | ... AL10: =AL9*'Model Inputs'!$D$118 -> 0
A11: Family Office Accounts (Y2+) | B11: ='Model Inputs'!B195 -> 0 | C11: ='Model Inputs'!C195 -> 0 | D11: ='Model Inputs'!D195 -> 0 | E11: ='Model Inputs'!E195 -> 0 | F11: ='Model Inputs'!F195 -> 0 | G11: ='Model Inputs'!G195 -> 0 | H11: ='Model Inputs'!H195 -> 0 | I11: ='Model Inputs'!I195 -> 0 | ... AK11: ='Model Inputs'!AK195 -> 2
A12: Family Office Seats | B12: =B11*'Model Inputs'!$B$119 -> 0 | C12: =C11*'Model Inputs'!$B$119 -> 0 | D12: =D11*'Model Inputs'!$B$119 -> 0 | E12: =E11*'Model Inputs'!$B$119 -> 0 | F12: =F11*'Model Inputs'!$B$119 -> 0 | G12: =G11*'Model Inputs'!$B$119 -> 0 | H12: =H11*'Model Inputs'!$B$119 -> 0 | I12: =I11*'Model Inputs'!$B$119 -> 0 | ... M12: =M11*'Model Inputs'!$B$119 -> 0 | N12: =N11*'Model Inputs'!$C$119 -> 0 | O12: =O11*'Model Inputs'!$C$119 -> 0 | P12: =P11*'Model Inputs'!$C$119 -> 0 | Q12: =Q11*'Model Inputs'!$C$119 -> 10 | R12: =R11*'Model Inputs'!$C$119 -> 10 | S12: =S11*'Model Inputs'!$C$119 -> 10 | T12: =T11*'Model Inputs'!$C$119 -> 10 | U12: =U11*'Model Inputs'!$C$119 -> 10 | ... Y12: =Y11*'Model Inputs'!$C$119 -> 10 | Z12: =Z11*'Model Inputs'!$D$119 -> 28 | AA12: =AA11*'Model Inputs'!$D$119 -> 28 | AB12: =AB11*'Model Inputs'!$D$119 -> 28 | AC12: =AC11*'Model Inputs'!$D$119 -> 28 | AD12: =AD11*'Model Inputs'!$D$119 -> 28 | AE12: =AE11*'Model Inputs'!$D$119 -> 28 | AF12: =AF11*'Model Inputs'!$D$119 -> 28 | AG12: =AG11*'Model Inputs'!$D$119 -> 28 | ... AL12: =AL11*'Model Inputs'!$D$119 -> 0
A13: General Legal Accounts (Y2+) | B13: ='Model Inputs'!B196 -> 0 | C13: ='Model Inputs'!C196 -> 0 | D13: ='Model Inputs'!D196 -> 0 | E13: ='Model Inputs'!E196 -> 0 | F13: ='Model Inputs'!F196 -> 0 | G13: ='Model Inputs'!G196 -> 0 | H13: ='Model Inputs'!H196 -> 0 | I13: ='Model Inputs'!I196 -> 0 | ... AK13: ='Model Inputs'!AK196 -> 2
A14: General Legal Seats | B14: =B13*'Model Inputs'!$B$120 -> 0 | C14: =C13*'Model Inputs'!$B$120 -> 0 | D14: =D13*'Model Inputs'!$B$120 -> 0 | E14: =E13*'Model Inputs'!$B$120 -> 0 | F14: =F13*'Model Inputs'!$B$120 -> 0 | G14: =G13*'Model Inputs'!$B$120 -> 0 | H14: =H13*'Model Inputs'!$B$120 -> 0 | I14: =I13*'Model Inputs'!$B$120 -> 0 | ... M14: =M13*'Model Inputs'!$B$120 -> 0 | N14: =N13*'Model Inputs'!$C$120 -> 35 | O14: =O13*'Model Inputs'!$C$120 -> 35 | P14: =P13*'Model Inputs'!$C$120 -> 35 | Q14: =Q13*'Model Inputs'!$C$120 -> 35 | R14: =R13*'Model Inputs'!$C$120 -> 35 | S14: =S13*'Model Inputs'!$C$120 -> 35 | T14: =T13*'Model Inputs'!$C$120 -> 35 | U14: =U13*'Model Inputs'!$C$120 -> 35 | ... Y14: =Y13*'Model Inputs'!$C$120 -> 70 | Z14: =Z13*'Model Inputs'!$D$120 -> 90 | AA14: =AA13*'Model Inputs'!$D$120 -> 90 | AB14: =AB13*'Model Inputs'!$D$120 -> 90 | AC14: =AC13*'Model Inputs'!$D$120 -> 90 | AD14: =AD13*'Model Inputs'!$D$120 -> 90 | AE14: =AE13*'Model Inputs'!$D$120 -> 90 | AF14: =AF13*'Model Inputs'!$D$120 -> 90 | AG14: =AG13*'Model Inputs'!$D$120 -> 90 | ... AL14: =AL13*'Model Inputs'!$D$120 -> 0
A15: Total Sales Accounts | B15: =B5+B7+B9+B11+B13+B18 -> 0 | C15: =C5+C7+C9+C11+C13+C18 -> 0 | D15: =D5+D7+D9+D11+D13+D18 -> 0 | E15: =E5+E7+E9+E11+E13+E18 -> 9 | F15: =F5+F7+F9+F11+F13+F18 -> 6 | G15: =G5+G7+G9+G11+G13+G18 -> 8 | H15: =H5+H7+H9+H11+H13+H18 -> 10 | I15: =I5+I7+I9+I11+I13+I18 -> 10 | ... AK15: =AK5+AK7+AK9+AK11+AK13+AK18 -> 27 | AL15: =AL5+AL7+AL9+AL11+AL13 -> 0
A16: Total Sales Seats | B16: =B6+B8+B10+B12+B14 -> 0 | C16: =C6+C8+C10+C12+C14 -> 0 | D16: =D6+D8+D10+D12+D14 -> 0 | E16: =E6+E8+E10+E12+E14 -> 220 | F16: =F6+F8+F10+F12+F14 -> 132 | G16: =G6+G8+G10+G12+G14 -> 198 | H16: =H6+H8+H10+H12+H14 -> 242 | I16: =I6+I8+I10+I12+I14 -> 242 | ... AL16: =AL6+AL8+AL10+AL12+AL14 -> 0
A17: Enterprise/MM Seats (Y2+) | B17: 0 | C17: 0 | D17: 0 | E17: 0 | F17: 0 | G17: 0 | H17: 0 | I17: 0 | J17: 0 | K17: 0 | L17: 0 | M17: 0 | N17: ='Model Inputs'!B148 -> 0 | O17: ='Model Inputs'!C148 -> 0 | P17: ='Model Inputs'!D148 -> 50 | Q17: ='Model Inputs'!E148 -> 50 | R17: ='Model Inputs'!F148 -> 50 | S17: ='Model Inputs'!G148 -> 100 | T17: ='Model Inputs'!H148 -> 100 | U17: ='Model Inputs'!I148 -> 100 | ... Y17: ='Model Inputs'!M148 -> 150 | Z17: ='Model Inputs'!B$145 -> 125 | AA17: ='Model Inputs'!C$145 -> 125 | AB17: ='Model Inputs'!D$145 -> 125 | AC17: ='Model Inputs'!E$145 -> 250 | AD17: ='Model Inputs'!F$145 -> 250 | AE17: ='Model Inputs'!G$145 -> 250 | AF17: ='Model Inputs'!H$145 -> 425 | AG17: ='Model Inputs'!I$145 -> 425 | ... AK17: ='Model Inputs'!M$145 -> 550
A18: Enterprise/MM Accounts (Y2+) | B18: 0 | C18: 0 | D18: 0 | E18: 0 | F18: 0 | G18: 0 | H18: 0 | I18: 0 | J18: 0 | K18: 0 | L18: 0 | M18: 0 | N18: ='Model Inputs'!B147 -> 0 | O18: ='Model Inputs'!C147 -> 0 | P18: ='Model Inputs'!D147 -> 1 | Q18: ='Model Inputs'!E147 -> 1 | R18: ='Model Inputs'!F147 -> 1 | S18: ='Model Inputs'!G147 -> 2 | T18: ='Model Inputs'!H147 -> 2 | U18: ='Model Inputs'!I147 -> 2 | ... Y18: ='Model Inputs'!M147 -> 3 | Z18: ='Model Inputs'!B144 -> 2 | AA18: ='Model Inputs'!C144 -> 2 | AB18: ='Model Inputs'!D144 -> 2 | AC18: ='Model Inputs'!E144 -> 4 | AD18: ='Model Inputs'!F144 -> 4 | AE18: ='Model Inputs'!G144 -> 4 | AF18: ='Model Inputs'!H144 -> 6 | AG18: ='Model Inputs'!I144 -> 6 | ... AK18: ='Model Inputs'!M144 -> 7
A19: PLG Accounts | B19: ='Model Inputs'!B20 -> 0 | C19: ='Model Inputs'!C20 -> 0 | D19: ='Model Inputs'!D20 -> 0 | E19: ='Model Inputs'!E20 -> 22 | F19: ='Model Inputs'!F20 -> 12 | G19: ='Model Inputs'!G20 -> 17 | H19: ='Model Inputs'!H20 -> 19 | I19: ='Model Inputs'!I20 -> 18 | ... AL19: ='Model Inputs'!AL20 -> 0
A20: PLG Seats | B20: ='Model Inputs'!B19 -> 0 | C20: ='Model Inputs'!C19 -> 0 | D20: ='Model Inputs'!D19 -> 0 | E20: ='Model Inputs'!E19 -> 22 | F20: ='Model Inputs'!F19 -> 13 | G20: ='Model Inputs'!G19 -> 20 | H20: ='Model Inputs'!H19 -> 24 | I20: ='Model Inputs'!I19 -> 24 | ... AL20: ='Model Inputs'!AL19 -> 0
A21: REFERRALS
A22: Referral Accounts | B22: 0 | C22: =ROUND(B35*'Model Inputs'!C41,0) -> 0 | D22: =ROUND(C35*'Model Inputs'!D41,0) -> 0 | E22: =ROUND(D35*'Model Inputs'!E41,0) -> 0 | F22: =ROUND(E35*'Model Inputs'!F41,0) -> 0 | G22: =ROUND(F35*'Model Inputs'!G41,0) -> 0 | H22: =ROUND(G35*'Model Inputs'!H41,0) -> 0 | I22: =ROUND(H35*'Model Inputs'!I41,0) -> 0 | J22: =ROUND(I35*'Model Inputs'!J41,0) -> 1 | ... AL22: =ROUND(AK35*'Model Inputs'!AL41,0) -> 11 | AM22: =ROUND(AL35*'Model Inputs'!$B$41,0) -> 5 | AN22: =ROUND(AM35*'Model Inputs'!$B$41,0) -> 0
A23: Referral Seats | B23: =B22*IF(1<=12,'Model Inputs'!$B$122,IF(1<=24,'Model Inputs'!$C$122,'Model Inputs'!$D$122)) -> 0 | C23: =C22*IF(2<=12,'Model Inputs'!$B$122,IF(2<=24,'Model Inputs'!$C$122,'Model Inputs'!$D$122)) -> 0 | D23: =D22*IF(3<=12,'Model Inputs'!$B$122,IF(3<=24,'Model Inputs'!$C$122,'Model Inputs'!$D$122)) -> 0 | E23: =E22*IF(4<=12,'Model Inputs'!$B$122,IF(4<=24,'Model Inputs'!$C$122,'Model Inputs'!$D$122)) -> 0 | F23: =F22*IF(5<=12,'Model Inputs'!$B$122,IF(5<=24,'Model Inputs'!$C$122,'Model Inputs'!$D$122)) -> 0 | G23: =G22*IF(6<=12,'Model Inputs'!$B$122,IF(6<=24,'Model Inputs'!$C$122,'Model Inputs'!$D$122)) -> 0 | H23: =H22*IF(7<=12,'Model Inputs'!$B$122,IF(7<=24,'Model Inputs'!$C$122,'Model Inputs'!$D$122)) -> 0 | I23: =I22*IF(8<=12,'Model Inputs'!$B$122,IF(8<=24,'Model Inputs'!$C$122,'Model Inputs'!$D$122)) -> 0 | J23: =J22*IF(9<=12,'Model Inputs'!$B$122,IF(9<=24,'Model Inputs'!$C$122,'Model Inputs'!$D$122)) -> 20 | K23: =K22*IF(10<=12,'Model Inputs'!$B$122,IF(10<=24,'Model Inputs'!$C$122,'Model Inputs'!$D$122)) -> 20 | L23: =L22*IF(11<=12,'Model Inputs'!$B$122,IF(11<=24,'Model Inputs'!$C$122,'Model Inputs'!$D$122)) -> 20 | M23: =M22*IF(12<=12,'Model Inputs'!$B$122,IF(12<=24,'Model Inputs'!$C$122,'Model Inputs'!$D$122)) -> 20 | N23: =N22*IF(13<=12,'Model Inputs'!$B$122,IF(13<=24,'Model Inputs'!$C$122,'Model Inputs'!$D$122)) -> 25 | O23: =O22*IF(14<=12,'Model Inputs'!$B$122,IF(14<=24,'Model Inputs'!$C$122,'Model Inputs'!$D$122)) -> 50 | P23: =P22*IF(15<=12,'Model Inputs'!$B$122,IF(15<=24,'Model Inputs'!$C$122,'Model Inputs'!$D$122)) -> 50 | Q23: =Q22*IF(16<=12,'Model Inputs'!$B$122,IF(16<=24,'Model Inputs'!$C$122,'Model Inputs'!$D$122)) -> 50 | R23: =R22*IF(17<=12,'Model Inputs'!$B$122,IF(17<=24,'Model Inputs'!$C$122,'Model Inputs'!$D$122)) -> 50 | S23: =S22*IF(18<=12,'Model Inputs'!$B$122,IF(18<=24,'Model Inputs'!$C$122,'Model Inputs'!$D$122)) -> 50 | T23: =T22*IF(19<=12,'Model Inputs'!$B$122,IF(19<=24,'Model Inputs'!$C$122,'Model Inputs'!$D$122)) -> 75 | U23: =U22*IF(20<=12,'Model Inputs'!$B$122,IF(20<=24,'Model Inputs'!$C$122,'Model Inputs'!$D$122)) -> 75 | V23: =V22*IF(21<=12,'Model Inputs'!$B$122,IF(21<=24,'Model Inputs'!$C$122,'Model Inputs'!$D$122)) -> 75 | W23: =W22*IF(22<=12,'Model Inputs'!$B$122,IF(22<=24,'Model Inputs'!$C$122,'Model Inputs'!$D$122)) -> 75 | X23: =X22*IF(23<=12,'Model Inputs'!$B$122,IF(23<=24,'Model Inputs'!$C$122,'Model Inputs'!$D$122)) -> 100 | Y23: =Y22*IF(24<=12,'Model Inputs'!$B$122,IF(24<=24,'Model Inputs'!$C$122,'Model Inputs'!$D$122)) -> 100 | Z23: =Z22*IF(25<=12,'Model Inputs'!$B$122,IF(25<=24,'Model Inputs'!$C$122,'Model Inputs'!$D$122)) -> 168 | AA23: =AA22*IF(26<=12,'Model Inputs'!$B$122,IF(26<=24,'Model Inputs'!$C$122,'Model Inputs'!$D$122)) -> 168 | AB23: =AB22*IF(27<=12,'Model Inputs'!$B$122,IF(27<=24,'Model Inputs'!$C$122,'Model Inputs'!$D$122)) -> 168 | AC23: =AC22*IF(28<=12,'Model Inputs'!$B$122,IF(28<=24,'Model Inputs'!$C$122,'Model Inputs'!$D$122)) -> 196 | AD23: =AD22*IF(29<=12,'Model Inputs'!$B$122,IF(29<=24,'Model Inputs'!$C$122,'Model Inputs'!$D$122)) -> 196 | AE23: =AE22*IF(30<=12,'Model Inputs'!$B$122,IF(30<=24,'Model Inputs'!$C$122,'Model Inputs'!$D$122)) -> 224 | AF23: =AF22*IF(31<=12,'Model Inputs'!$B$122,IF(31<=24,'Model Inputs'!$C$122,'Model Inputs'!$D$122)) -> 224 | AG23: =AG22*IF(32<=12,'Model Inputs'!$B$122,IF(32<=24,'Model Inputs'!$C$122,'Model Inputs'!$D$122)) -> 224 | AH23: =AH22*IF(33<=12,'Model Inputs'!$B$122,IF(33<=24,'Model Inputs'!$C$122,'Model Inputs'!$D$122)) -> 252 | AI23: =AI22*IF(34<=12,'Model Inputs'!$B$122,IF(34<=24,'Model Inputs'!$C$122,'Model Inputs'!$D$122)) -> 252 | AJ23: =AJ22*IF(35<=12,'Model Inputs'!$B$122,IF(35<=24,'Model Inputs'!$C$122,'Model Inputs'!$D$122)) -> 280 | AK23: =AK22*IF(36<=12,'Model Inputs'!$B$122,IF(36<=24,'Model Inputs'!$C$122,'Model Inputs'!$D$122)) -> 280 | AL23: =AL22*IF(37<=12,'Model Inputs'!$B$122,IF(37<=24,'Model Inputs'!$C$122,'Model Inputs'!$D$122)) -> 308 | AM23: =AM22*IF(38<=12,'Model Inputs'!$B$122,IF(38<=24,'Model Inputs'!$C$122,'Model Inputs'!$D$122)) -> 140 | AN23: =AN22*IF(39<=12,'Model Inputs'!$B$122,IF(39<=24,'Model Inputs'!$C$122,'Model Inputs'!$D$122)) -> 0
A24: SEAT METRICS
A25: Previous Active Seats | B25: 0 | C25: =B28 -> 0 | D25: =C28 -> 0 | E25: =D28 -> 0 | F25: =E28 -> 242 | G25: =F28 -> 386 | H25: =G28 -> 602 | I25: =H28 -> 866 | J25: =I28 -> 1129 | ... AL25: =AK28 -> 23091
A26: Churned Seats | B26: =ROUND(B25*'Model Inputs'!$E$41,0) -> 0 | C26: =ROUND(C25*'Model Inputs'!$E$41,0) -> 0 | D26: =ROUND(D25*'Model Inputs'!$E$41,0) -> 0 | E26: =ROUND(E25*'Model Inputs'!$E$41,0) -> 0 | F26: =ROUND(F25*'Model Inputs'!$E$41,0) -> 1 | G26: =ROUND(G25*'Model Inputs'!$E$41,0) -> 2 | H26: =ROUND(H25*'Model Inputs'!$E$41,0) -> 2 | I26: =ROUND(I25*'Model Inputs'!$E$41,0) -> 3 | ... AN26: =ROUND(AN25*'Model Inputs'!$E$41,0) -> 0
A27: New Seats (Total) | B27: =B16+B17+B20+B23 -> 0 | C27: =C16+C17+C20+C23 -> 0 | D27: =D16+D17+D20+D23 -> 0 | E27: =E16+E17+E20+E23 -> 242 | F27: =F16+F17+F20+F23 -> 145 | G27: =G16+G17+G20+G23 -> 218 | H27: =H16+H17+H20+H23 -> 266 | I27: =I16+I17+I20+I23 -> 266 | ... AL27: =AL16+AL17+AL20+AL23 -> 308
A28: Active Seats (EOP) | B28: =B25-B26+B27 -> 0 | C28: =C25-C26+C27 -> 0 | D28: =D25-D26+D27 -> 0 | E28: =E25-E26+E27 -> 242 | F28: =F25-F26+F27 -> 386 | G28: =G25-G26+G27 -> 602 | H28: =H25-H26+H27 -> 866 | I28: =I25-I26+I27 -> 1129 | ... AL28: =AL25-AL26+AL27 -> 23307
A29: REVENUE
A30: Blended Effective Rate | B30: =IF(B16+B20+B23>0,(B6*'Model Inputs'!$B$7+B8*'Model Inputs'!$B$8+B10*'Model Inputs'!$B$8+B12*'Model Inputs'!$B$7+B14*'Model Inputs'!$B$8+B20*15+B23*'Model Inputs'!$B$7)/(B16+B20+B23),0) -> 0 | C30: =IF(C16+C20+C23>0,(C6*'Model Inputs'!$B$7+C8*'Model Inputs'!$B$8+C10*'Model Inputs'!$B$8+C12*'Model Inputs'!$B$7+C14*'Model Inputs'!$B$8+C20*15+C23*'Model Inputs'!$B$7)/(C16+C20+C23),0) -> 0 | D30: =IF(D16+D20+D23>0,(D6*'Model Inputs'!$B$7+D8*'Model Inputs'!$B$8+D10*'Model Inputs'!$B$8+D12*'Model Inputs'!$B$7+D14*'Model Inputs'!$B$8+D20*15+D23*'Model Inputs'!$B$7)/(D16+D20+D23),0) -> 0 | E30: =IF(E16+E20+E23>0,(E6*'Model Inputs'!$B$7+E8*'Model Inputs'!$B$8+E10*'Model Inputs'!$B$8+E12*'Model Inputs'!$B$7+E14*'Model Inputs'!$B$8+E20*15+E23*'Model Inputs'!$B$7)/(E16+E20+E23),0) -> 29.545455 | F30: =IF(F16+F20+F23>0,(F6*'Model Inputs'!$B$7+F8*'Model Inputs'!$B$8+F10*'Model Inputs'!$B$8+F12*'Model Inputs'!$B$7+F14*'Model Inputs'!$B$8+F20*15+F23*'Model Inputs'!$B$7)/(F16+F20+F23),0) -> 27.744828 | G30: =IF(G16+G20+G23>0,(G6*'Model Inputs'!$B$7+G8*'Model Inputs'!$B$8+G10*'Model Inputs'!$B$8+G12*'Model Inputs'!$B$7+G14*'Model Inputs'!$B$8+G20*15+G23*'Model Inputs'!$B$7)/(G16+G20+G23),0) -> 29.733945 | H30: =IF(H16+H20+H23>0,(H6*'Model Inputs'!$B$7+H8*'Model Inputs'!$B$8+H10*'Model Inputs'!$B$8+H12*'Model Inputs'!$B$7+H14*'Model Inputs'!$B$8+H20*15+H23*'Model Inputs'!$B$7)/(H16+H20+H23),0) -> 29.390977 | I30: =IF(I16+I20+I23>0,(I6*'Model Inputs'!$B$7+I8*'Model Inputs'!$B$8+I10*'Model Inputs'!$B$8+I12*'Model Inputs'!$B$7+I14*'Model Inputs'!$B$8+I20*15+I23*'Model Inputs'!$B$7)/(I16+I20+I23),0) -> 29.390977 | ... AL30: =IF(AL16+AL20+AL23>0,(AL6*'Model Inputs'!$B$7+AL8*'Model Inputs'!$B$8+AL10*'Model Inputs'!$B$8+AL12*'Model Inputs'!$B$7+AL14*'Model Inputs'!$B$8+AL20*15+AL23*'Model Inputs'!$B$7)/(AL16+AL20+AL23),0) -> 29
A31: MRR | B31: =B28*B30 -> 0 | C31: =C28*C30 -> 0 | D31: =D28*D30 -> 0 | E31: =E28*E30 -> 7150 | F31: =F28*F30 -> 10709.503 | G31: =G28*G30 -> 17899.835 | H31: =H28*H30 -> 25452.586 | I31: =I28*I30 -> 33182.414 | ... Y31: =Y28*Y30 -> 275874.33 | Z31: =(Z28-Z17)*Z30+'Model Inputs'!B$146 -> 309107.62 | AA31: =(AA28-AA17)*AA30+'Model Inputs'!C$146 -> 337831.58 | AB31: =(AB28-AB17)*AB30+'Model Inputs'!D$146 -> 366431.74 | AC31: =(AC28-AC17)*AC30+'Model Inputs'!E$146 -> 399887.94 | AD31: =(AD28-AD17)*AD30+'Model Inputs'!F$146 -> 432909.12 | AE31: =(AE28-AE17)*AE30+'Model Inputs'!G$146 -> 465801.02 | AF31: =(AF28-AF17)*AF30+'Model Inputs'!H$146 -> 507450.89 | AG31: =(AG28-AG17)*AG30+'Model Inputs'!I$146 -> 546267.02 | ... AL31: =(AL28-AL17)*AL30+'Model Inputs'!N$146 -> 675903
A32: ARR (MRR × 12) | B32: =B31*12 -> 0 | C32: =C31*12 -> 0 | D32: =D31*12 -> 0 | E32: =E31*12 -> 85800 | F32: =F31*12 -> 128514.04 | G32: =G31*12 -> 214798.02 | H32: =H31*12 -> 305431.04 | I32: =I31*12 -> 398188.96 | ... AL32: =AL31*12 -> 8110836
A33: ACCOUNT METRICS
A34: Total New Accounts | B34: =B15+B19+B22 -> 0 | C34: =C15+C19+C22 -> 0 | D34: =D15+D19+D22 -> 0 | E34: =E15+E19+E22 -> 31 | F34: =F15+F19+F22 -> 18 | G34: =G15+G19+G22 -> 25 | H34: =H15+H19+H22 -> 29 | I34: =I15+I19+I22 -> 28 | ... AL34: =AL15+AL19+AL22 -> 11
A35: Cumulative Accounts | B35: =B34 -> 0 | C35: =B35+C34 -> 0 | D35: =C35+D34 -> 0 | E35: =D35+E34 -> 31 | F35: =E35+F34 -> 49 | G35: =F35+G34 -> 74 | H35: =G35+H34 -> 103 | I35: =H35+I34 -> 131 | J35: =I35+J34 -> 159 | ... AL35: =AK35+AL34 -> 1328
A36: Avg Seats/Account | B36: =IF(B35>0,B28/B35,0) -> 0 | C36: =IF(C35>0,C28/C35,0) -> 0 | D36: =IF(D35>0,D28/D35,0) -> 0 | E36: =IF(E35>0,E28/E35,0) -> 7.8064516 | F36: =IF(F35>0,F28/F35,0) -> 7.877551 | G36: =IF(G35>0,G28/G35,0) -> 8.1351351 | H36: =IF(H35>0,H28/H35,0) -> 8.407767 | I36: =IF(I35>0,I28/I35,0) -> 8.6183206 | ... AL36: =IF(AL35>0,AL28/AL35,0) -> 17.550452
A37: Sales MRR (excl. PLG/Referrals) | E37: =E6*'Model Inputs'!$B$7+E8*'Model Inputs'!$B$8+E10*'Model Inputs'!$B$8+E12*'Model Inputs'!$B$7+E14*'Model Inputs'!$B$8 -> 6820 | F37: =F6*'Model Inputs'!$B$7+F8*'Model Inputs'!$B$8+F10*'Model Inputs'!$B$8+F12*'Model Inputs'!$B$7+F14*'Model Inputs'!$B$8 -> 3828 | G37: =G6*'Model Inputs'!$B$7+G8*'Model Inputs'!$B$8+G10*'Model Inputs'!$B$8+G12*'Model Inputs'!$B$7+G14*'Model Inputs'!$B$8 -> 6182 | H37: =H6*'Model Inputs'!$B$7+H8*'Model Inputs'!$B$8+H10*'Model Inputs'!$B$8+H12*'Model Inputs'!$B$7+H14*'Model Inputs'!$B$8 -> 7458 | I37: =I6*'Model Inputs'!$B$7+I8*'Model Inputs'!$B$8+I10*'Model Inputs'!$B$8+I12*'Model Inputs'!$B$7+I14*'Model Inputs'!$B$8 -> 7458 | J37: =J6*'Model Inputs'!$B$7+J8*'Model Inputs'!$B$8+J10*'Model Inputs'!$B$8+J12*'Model Inputs'!$B$7+J14*'Model Inputs'!$B$8 -> 7458 | K37: =K6*'Model Inputs'!$B$7+K8*'Model Inputs'!$B$8+K10*'Model Inputs'!$B$8+K12*'Model Inputs'!$B$7+K14*'Model Inputs'!$B$8 -> 7458 | L37: =L6*'Model Inputs'!$B$7+L8*'Model Inputs'!$B$8+L10*'Model Inputs'!$B$8+L12*'Model Inputs'!$B$7+L14*'Model Inputs'!$B$8 -> 7458 | ... AN37: =AN6*'Model Inputs'!$B$7+AN8*'Model Inputs'!$B$8+AN10*'Model Inputs'!$B$8+AN12*'Model Inputs'!$B$7+AN14*'Model Inputs'!$B$8 -> 0
A40: BOTTOM-UP MODEL ASSUMPTIONS & METHODOLOGY
A42: 1. SALES CAPACITY LOGIC
A43: Parameter | B43: Value | C43: Rationale
A44: Founder Capacity | B44: 5 deals/mo | C44: ~50% sales focus (balance: product, fundraising, ops)
A45: AE Capacity | B45: 8 deals/mo | C45: 100% sales focus = ~$1.9M quota at $20K ACV
A46: Capacity Ratio | B46: 1.6x | C46: AE vs Founder reflects full-time focus differential
A47: AE Ramp Period | B47: 4 months | C47: 25% → 50% → 75% → 100% capacity progression
A48: AE1 Start | B48: M4 | C48: Hired pre-launch to hit ground running at launch
A49: Execution Rate | B49: 70% → 85% | C49: Improves +1%/mo as sales process matures
A51: 2. VERTICAL ALLOCATION
A52: Vertical | B52: Y1 | C52: Y2 | D52: Y3 | E52: Seats/Acct | F52: ACV
A53: Crypto/Web3 (incl. FinTech) | B53: 93% | C53: 70% | D53: 60% | E53: 22→28 | F53: $10,296
A54: Crypto Law | B54: 7% | C54: 8% | D54: 9% | E54: 44→60 | F54: $20,592
A55: Healthcare | B55: 0% | C55: 10% | D55: 12% | E55: 15→20 | F55: $7,020
A56: Family Office | B56: 0% | C56: 5% | D56: 8% | E56: 10→14 | F56: $4,680
A57: General Legal | B57: 0% | C57: 7% | D57: 11% | E57: 35→45 | F57: $16,380
A58: Note: FinTech (1-2%) consolidated into Crypto/Web3 for simplicity.
A59: FinTech/Healthcare require SOC 2 Type II & HIPAA (Y2M1).
A60: Certifications: SOC 2 Type I, SOC 2 Type II, HIPAA — all target Y2M1.
A61: 3. PRICING STRATEGY
A62: Tier | B62: $/Seat/Mo | C62: Min Seats | D62: Target Market
A63: Pro | B63: $9 | C63: 1 | D63: Privacy individuals (PLG)
A64: Power User | B64: $49 | C64: 1 | D64: Creatives/power users (PLG)
A65: Scale | B65: $29 | C65: 2+ | D65: SMB/boutique teams
A66: Mid-Market | B66: $39 | C66: 50+ | D66: Sales-led, SSO/Invoicing
A67: Enterprise | B67: $49 | C67: 100+ | D67: White glove, SLA
A69: Contract Mix | B69: 50% Monthly | C69: 15% Quarterly | D69: 35% Annual
A70: Benchmark: Industry avg 40/11/42. Higher monthly reflects SMB crypto early adopters.
A71: 4. PLG CHANNEL
A72: Metric | B72: Value | C72: Rationale
A73: PLG Seat % | B73: 10% of Sales | C73: Organic crypto maxis finding product
A74: PLG Tier Mix (Y1) | B74: 80% Pro / 20% Power | C74: Individual users dominate early
A75: PLG Tier Mix (Y2) | B75: 70% Pro / 30% Power | C75: Power users grow with brand
A76: PLG Tier Mix (Y3) | B76: 60% Pro / 40% Power | C76: More power users as product matures
A77: Blended PLG Price | B77: $17→$25 | C77: Y1 to Y3 progression
A79: 5. REFERRAL CHANNEL
A80: Year | B80: Monthly Rate | C80: Annual Equiv | D80: Channel Mix
A81: Y1 | B81: 0.4% | C81: ~5% | D81: ~2%
A82: Y2 | B82: 0.6% | C82: ~7% | D82: ~8%
A83: Y3 | B83: 0.8% | C83: ~10% | D83: ~19%
A84: Applied to cumulative account base. Referral seats match sales profile (~20/acct).
A86: 6. CHURN ASSUMPTIONS
A87: Metric | B87: Y1 | C87: Y2 | D87: Y3 | E87: Rationale
A88: Monthly Seat Churn | B88: 2.0% | C88: 1.5% | D88: 1.2% | E88: Improves with product maturity
A89: Annual Equivalent | B89: ~22% | C89: ~17% | D89: ~14% | E89: Below SMB avg (3-5% monthly)
A91: 7. TARGET UNIT ECONOMICS
A92: Metric | B92: Target | C92: Notes
A93: Gross Margin | B93: 85%+ | C93: IPFS infrastructure efficiency
A94: CAC Payback | B94: <12 months | C94: Based on ACV and sales cost
A95: LTV:CAC | B95: >3:1 | C95: Healthy unit economics threshold
A97: Notes:
A98: • Quota benchmark: Mid-market AE typically $750K-$1.5M; our $1.9M justified by focused beachhead
A99: • Crypto law firms serve crypto clients → natural referral channel → interconnected beachhead
A100: • Lower churn reflects: compliance-driven stickiness, enterprise focus, ZK lock-in
A101: • PLG measured as % of sales SEATS, not accounts (apples-to-apples comparison)
A102: • All projections formula-driven from Model Inputs tab. Adjust inputs to run scenarios.

Sheet COGS Analysis
A1: COGS ANALYSIS - 36-MONTH DETAIL
A3: Component | B3: Y1M1 | C3: Y1M2 | D3: Y1M3 | E3: Y1M4 | F3: Y1M5 | G3: Y1M6 | H3: Y1M7 | I3: Y1M8 | J3: Y1M9 | K3: Y1M10 | L3: Y1M11 | M3: Y1M12 | N3: Y2M1 | O3: Y2M2 | P3: Y2M3 | Q3: Y2M4 | R3: Y2M5 | S3: Y2M6 | T3: Y2M7 | U3: Y2M8 | V3: Y2M9 | W3: Y2M10 | X3: Y2M11 | Y3: Y2M12 | Z3: Y3M1 | AA3: Y3M2 | AB3: Y3M3 | AC3: Y3M4 | AD3: Y3M5 | AE3: Y3M6 | AF3: Y3M7 | AG3: Y3M8 | AH3: Y3M9 | AI3: Y3M10 | AJ3: Y3M11 | AK3: Y3M12
A4: VARIABLE COSTS (Scale with seats)
A5: Storage | B5: ='Revenue Model'!B$28*'Model Inputs'!$B$60 -> 0 | C5: ='Revenue Model'!C$28*'Model Inputs'!$B$60 -> 0 | D5: ='Revenue Model'!D$28*'Model Inputs'!$B$60 -> 0 | E5: ='Revenue Model'!E$28*'Model Inputs'!$B$60 -> 822.8 | F5: ='Revenue Model'!F$28*'Model Inputs'!$B$60 -> 1312.4 | G5: ='Revenue Model'!G$28*'Model Inputs'!$B$60 -> 2046.8 | H5: ='Revenue Model'!H$28*'Model Inputs'!$B$60 -> 2944.4 | I5: ='Revenue Model'!I$28*'Model Inputs'!$B$60 -> 3838.6 | ... M5: ='Revenue Model'!M$28*'Model Inputs'!$B$60 -> 7639.8 | N5: ='Revenue Model'!N$28*'Model Inputs'!$C$60 -> 6928.2 | O5: ='Revenue Model'!O$28*'Model Inputs'!$C$60 -> 7854.3 | P5: ='Revenue Model'!P$28*'Model Inputs'!$C$60 -> 8910 | Q5: ='Revenue Model'!Q$28*'Model Inputs'!$C$60 -> 10065.6 | R5: ='Revenue Model'!R$28*'Model Inputs'!$C$60 -> 11291.4 | S5: ='Revenue Model'!S$28*'Model Inputs'!$C$60 -> 12838.5 | T5: ='Revenue Model'!T$28*'Model Inputs'!$C$60 -> 14523.3 | U5: ='Revenue Model'!U$28*'Model Inputs'!$C$60 -> 16200 | ... Y5: ='Revenue Model'!Y$28*'Model Inputs'!$C$60 -> 24359.4 | Z5: ='Revenue Model'!Z$28*'Model Inputs'!$D$60 -> 20704.32 | AA5: ='Revenue Model'!AA$28*'Model Inputs'!$D$60 -> 22634.56 | AB5: ='Revenue Model'!AB$28*'Model Inputs'!$D$60 -> 24556.48 | AC5: ='Revenue Model'!AC$28*'Model Inputs'!$D$60 -> 26790.4 | AD5: ='Revenue Model'!AD$28*'Model Inputs'!$D$60 -> 29013.92 | AE5: ='Revenue Model'!AE$28*'Model Inputs'!$D$60 -> 31287.36 | AF5: ='Revenue Model'!AF$28*'Model Inputs'!$D$60 -> 33916.48 | AG5: ='Revenue Model'!AG$28*'Model Inputs'!$D$60 -> 36535.2 | ... AL5: ='Revenue Model'!AL$28*'Model Inputs'!$D$60 -> 48478.56
A6: Bandwidth | B6: ='Revenue Model'!B$28*'Model Inputs'!$B$61 -> 0 | C6: ='Revenue Model'!C$28*'Model Inputs'!$B$61 -> 0 | D6: ='Revenue Model'!D$28*'Model Inputs'!$B$61 -> 0 | E6: ='Revenue Model'!E$28*'Model Inputs'!$B$61 -> 174.24 | F6: ='Revenue Model'!F$28*'Model Inputs'!$B$61 -> 277.92 | G6: ='Revenue Model'!G$28*'Model Inputs'!$B$61 -> 433.44 | H6: ='Revenue Model'!H$28*'Model Inputs'!$B$61 -> 623.52 | I6: ='Revenue Model'!I$28*'Model Inputs'!$B$61 -> 812.88 | ... M6: ='Revenue Model'!M$28*'Model Inputs'!$B$61 -> 1617.84 | N6: ='Revenue Model'!N$28*'Model Inputs'!$C$61 -> 1206.02 | O6: ='Revenue Model'!O$28*'Model Inputs'!$C$61 -> 1367.23 | P6: ='Revenue Model'!P$28*'Model Inputs'!$C$61 -> 1551 | Q6: ='Revenue Model'!Q$28*'Model Inputs'!$C$61 -> 1752.16 | R6: ='Revenue Model'!R$28*'Model Inputs'!$C$61 -> 1965.54 | S6: ='Revenue Model'!S$28*'Model Inputs'!$C$61 -> 2234.85 | T6: ='Revenue Model'!T$28*'Model Inputs'!$C$61 -> 2528.13 | U6: ='Revenue Model'!U$28*'Model Inputs'!$C$61 -> 2820 | ... Y6: ='Revenue Model'!Y$28*'Model Inputs'!$C$61 -> 4240.34 | Z6: ='Revenue Model'!Z$28*'Model Inputs'!$D$61 -> 3085.74 | AA6: ='Revenue Model'!AA$28*'Model Inputs'!$D$61 -> 3373.42 | AB6: ='Revenue Model'!AB$28*'Model Inputs'!$D$61 -> 3659.86 | AC6: ='Revenue Model'!AC$28*'Model Inputs'!$D$61 -> 3992.8 | AD6: ='Revenue Model'!AD$28*'Model Inputs'!$D$61 -> 4324.19 | AE6: ='Revenue Model'!AE$28*'Model Inputs'!$D$61 -> 4663.02 | AF6: ='Revenue Model'!AF$28*'Model Inputs'!$D$61 -> 5054.86 | AG6: ='Revenue Model'!AG$28*'Model Inputs'!$D$61 -> 5445.15 | ... AL6: ='Revenue Model'!AL$28*'Model Inputs'!$D$61 -> 7225.17
A7: Compute | B7: ='Revenue Model'!B$28*'Model Inputs'!$B$62 -> 0 | C7: ='Revenue Model'!C$28*'Model Inputs'!$B$62 -> 0 | D7: ='Revenue Model'!D$28*'Model Inputs'!$B$62 -> 0 | E7: ='Revenue Model'!E$28*'Model Inputs'!$B$62 -> 29.04 | F7: ='Revenue Model'!F$28*'Model Inputs'!$B$62 -> 46.32 | G7: ='Revenue Model'!G$28*'Model Inputs'!$B$62 -> 72.24 | H7: ='Revenue Model'!H$28*'Model Inputs'!$B$62 -> 103.92 | I7: ='Revenue Model'!I$28*'Model Inputs'!$B$62 -> 135.48 | ... M7: ='Revenue Model'!M$28*'Model Inputs'!$B$62 -> 269.64 | N7: ='Revenue Model'!N$28*'Model Inputs'!$C$62 -> 205.28 | O7: ='Revenue Model'!O$28*'Model Inputs'!$C$62 -> 232.72 | P7: ='Revenue Model'!P$28*'Model Inputs'!$C$62 -> 264 | Q7: ='Revenue Model'!Q$28*'Model Inputs'!$C$62 -> 298.24 | R7: ='Revenue Model'!R$28*'Model Inputs'!$C$62 -> 334.56 | S7: ='Revenue Model'!S$28*'Model Inputs'!$C$62 -> 380.4 | T7: ='Revenue Model'!T$28*'Model Inputs'!$C$62 -> 430.32 | U7: ='Revenue Model'!U$28*'Model Inputs'!$C$62 -> 480 | ... Y7: ='Revenue Model'!Y$28*'Model Inputs'!$C$62 -> 721.76 | Z7: ='Revenue Model'!Z$28*'Model Inputs'!$D$62 -> 597.24 | AA7: ='Revenue Model'!AA$28*'Model Inputs'!$D$62 -> 652.92 | AB7: ='Revenue Model'!AB$28*'Model Inputs'!$D$62 -> 708.36 | AC7: ='Revenue Model'!AC$28*'Model Inputs'!$D$62 -> 772.8 | AD7: ='Revenue Model'!AD$28*'Model Inputs'!$D$62 -> 836.94 | AE7: ='Revenue Model'!AE$28*'Model Inputs'!$D$62 -> 902.52 | AF7: ='Revenue Model'!AF$28*'Model Inputs'!$D$62 -> 978.36 | AG7: ='Revenue Model'!AG$28*'Model Inputs'!$D$62 -> 1053.9 | ... AL7: ='Revenue Model'!AL$28*'Model Inputs'!$D$62 -> 1398.42
A8: Data Replication | B8: ='Revenue Model'!B$28*'Model Inputs'!$B$63 -> 0 | C8: ='Revenue Model'!C$28*'Model Inputs'!$B$63 -> 0 | D8: ='Revenue Model'!D$28*'Model Inputs'!$B$63 -> 0 | E8: ='Revenue Model'!E$28*'Model Inputs'!$B$63 -> 58.08 | F8: ='Revenue Model'!F$28*'Model Inputs'!$B$63 -> 92.64 | G8: ='Revenue Model'!G$28*'Model Inputs'!$B$63 -> 144.48 | H8: ='Revenue Model'!H$28*'Model Inputs'!$B$63 -> 207.84 | I8: ='Revenue Model'!I$28*'Model Inputs'!$B$63 -> 270.96 | ... M8: ='Revenue Model'!M$28*'Model Inputs'!$B$63 -> 539.28 | N8: ='Revenue Model'!N$28*'Model Inputs'!$C$63 -> 461.88 | O8: ='Revenue Model'!O$28*'Model Inputs'!$C$63 -> 523.62 | P8: ='Revenue Model'!P$28*'Model Inputs'!$C$63 -> 594 | Q8: ='Revenue Model'!Q$28*'Model Inputs'!$C$63 -> 671.04 | R8: ='Revenue Model'!R$28*'Model Inputs'!$C$63 -> 752.76 | S8: ='Revenue Model'!S$28*'Model Inputs'!$C$63 -> 855.9 | T8: ='Revenue Model'!T$28*'Model Inputs'!$C$63 -> 968.22 | U8: ='Revenue Model'!U$28*'Model Inputs'!$C$63 -> 1080 | ... Y8: ='Revenue Model'!Y$28*'Model Inputs'!$C$63 -> 1623.96 | Z8: ='Revenue Model'!Z$28*'Model Inputs'!$D$63 -> 1393.56 | AA8: ='Revenue Model'!AA$28*'Model Inputs'!$D$63 -> 1523.48 | AB8: ='Revenue Model'!AB$28*'Model Inputs'!$D$63 -> 1652.84 | AC8: ='Revenue Model'!AC$28*'Model Inputs'!$D$63 -> 1803.2 | AD8: ='Revenue Model'!AD$28*'Model Inputs'!$D$63 -> 1952.86 | AE8: ='Revenue Model'!AE$28*'Model Inputs'!$D$63 -> 2105.88 | AF8: ='Revenue Model'!AF$28*'Model Inputs'!$D$63 -> 2282.84 | AG8: ='Revenue Model'!AG$28*'Model Inputs'!$D$63 -> 2459.1 | ... AL8: ='Revenue Model'!AL$28*'Model Inputs'!$D$63 -> 3262.98
A9: Support Automation | B9: ='Revenue Model'!B$28*'Model Inputs'!$B$64 -> 0 | C9: ='Revenue Model'!C$28*'Model Inputs'!$B$64 -> 0 | D9: ='Revenue Model'!D$28*'Model Inputs'!$B$64 -> 0 | E9: ='Revenue Model'!E$28*'Model Inputs'!$B$64 -> 0 | F9: ='Revenue Model'!F$28*'Model Inputs'!$B$64 -> 0 | G9: ='Revenue Model'!G$28*'Model Inputs'!$B$64 -> 0 | H9: ='Revenue Model'!H$28*'Model Inputs'!$B$64 -> 0 | I9: ='Revenue Model'!I$28*'Model Inputs'!$B$64 -> 0 | ... M9: ='Revenue Model'!M$28*'Model Inputs'!$B$64 -> 0 | N9: ='Revenue Model'!N$28*'Model Inputs'!$C$64 -> 153.96 | O9: ='Revenue Model'!O$28*'Model Inputs'!$C$64 -> 174.54 | P9: ='Revenue Model'!P$28*'Model Inputs'!$C$64 -> 198 | Q9: ='Revenue Model'!Q$28*'Model Inputs'!$C$64 -> 223.68 | R9: ='Revenue Model'!R$28*'Model Inputs'!$C$64 -> 250.92 | S9: ='Revenue Model'!S$28*'Model Inputs'!$C$64 -> 285.3 | T9: ='Revenue Model'!T$28*'Model Inputs'!$C$64 -> 322.74 | U9: ='Revenue Model'!U$28*'Model Inputs'!$C$64 -> 360 | ... Y9: ='Revenue Model'!Y$28*'Model Inputs'!$C$64 -> 541.32 | Z9: ='Revenue Model'!Z$28*'Model Inputs'!$D$64 -> 398.16 | AA9: ='Revenue Model'!AA$28*'Model Inputs'!$D$64 -> 435.28 | AB9: ='Revenue Model'!AB$28*'Model Inputs'!$D$64 -> 472.24 | AC9: ='Revenue Model'!AC$28*'Model Inputs'!$D$64 -> 515.2 | AD9: ='Revenue Model'!AD$28*'Model Inputs'!$D$64 -> 557.96 | AE9: ='Revenue Model'!AE$28*'Model Inputs'!$D$64 -> 601.68 | AF9: ='Revenue Model'!AF$28*'Model Inputs'!$D$64 -> 652.24 | AG9: ='Revenue Model'!AG$28*'Model Inputs'!$D$64 -> 702.6 | ... AL9: ='Revenue Model'!AL$28*'Model Inputs'!$D$64 -> 932.28
A10: Blockchain Gas (SOL) | B10: ='Revenue Model'!B$28*'Model Inputs'!$B$66 -> 0 | C10: ='Revenue Model'!C$28*'Model Inputs'!$B$66 -> 0 | D10: ='Revenue Model'!D$28*'Model Inputs'!$B$66 -> 0 | E10: ='Revenue Model'!E$28*'Model Inputs'!$B$66 -> 2.42 | F10: ='Revenue Model'!F$28*'Model Inputs'!$B$66 -> 3.86 | G10: ='Revenue Model'!G$28*'Model Inputs'!$B$66 -> 6.02 | H10: ='Revenue Model'!H$28*'Model Inputs'!$B$66 -> 8.66 | I10: ='Revenue Model'!I$28*'Model Inputs'!$B$66 -> 11.29 | ... M10: ='Revenue Model'!M$28*'Model Inputs'!$B$66 -> 22.47 | N10: ='Revenue Model'!N$28*'Model Inputs'!$C$66 -> 20.528 | O10: ='Revenue Model'!O$28*'Model Inputs'!$C$66 -> 23.272 | P10: ='Revenue Model'!P$28*'Model Inputs'!$C$66 -> 26.4 | Q10: ='Revenue Model'!Q$28*'Model Inputs'!$C$66 -> 29.824 | R10: ='Revenue Model'!R$28*'Model Inputs'!$C$66 -> 33.456 | S10: ='Revenue Model'!S$28*'Model Inputs'!$C$66 -> 38.04 | T10: ='Revenue Model'!T$28*'Model Inputs'!$C$66 -> 43.032 | U10: ='Revenue Model'!U$28*'Model Inputs'!$C$66 -> 48 | ... Y10: ='Revenue Model'!Y$28*'Model Inputs'!$C$66 -> 72.176 | Z10: ='Revenue Model'!Z$28*'Model Inputs'!$D$66 -> 59.724 | AA10: ='Revenue Model'!AA$28*'Model Inputs'!$D$66 -> 65.292 | AB10: ='Revenue Model'!AB$28*'Model Inputs'!$D$66 -> 70.836 | AC10: ='Revenue Model'!AC$28*'Model Inputs'!$D$66 -> 77.28 | AD10: ='Revenue Model'!AD$28*'Model Inputs'!$D$66 -> 83.694 | AE10: ='Revenue Model'!AE$28*'Model Inputs'!$D$66 -> 90.252 | AF10: ='Revenue Model'!AF$28*'Model Inputs'!$D$66 -> 97.836 | AG10: ='Revenue Model'!AG$28*'Model Inputs'!$D$66 -> 105.39 | ... AK10: ='Revenue Model'!AK$28*'Model Inputs'!$D$66 -> 138.546
A11: Payment Processing (2.9%) | B11: ='Revenue Model'!B$31*'Model Inputs'!$B$65 -> 0 | C11: ='Revenue Model'!C$31*'Model Inputs'!$B$65 -> 0 | D11: ='Revenue Model'!D$31*'Model Inputs'!$B$65 -> 0 | E11: ='Revenue Model'!E$31*'Model Inputs'!$B$65 -> 207.35 | F11: ='Revenue Model'!F$31*'Model Inputs'!$B$65 -> 310.5756 | G11: ='Revenue Model'!G$31*'Model Inputs'!$B$65 -> 519.09521 | H11: ='Revenue Model'!H$31*'Model Inputs'!$B$65 -> 738.12501 | I11: ='Revenue Model'!I$31*'Model Inputs'!$B$65 -> 962.28999 | ... AK11: ='Revenue Model'!AK$31*'Model Inputs'!$B$65 -> 20778.203 | AL11: ='Revenue Model'!AL$31*'Model Inputs'!$D$65 -> 19601.187
A12: STEP-FUNCTION COSTS (Tier-Based)
A13: Filebase Platform | B13: 0 | C13: 0 | D13: 0 | E13: ='Model Inputs'!$B$69 -> 1500 | F13: ='Model Inputs'!$B$69 -> 1500 | G13: ='Model Inputs'!$B$69 -> 1500 | H13: ='Model Inputs'!$B$69 -> 1500 | I13: ='Model Inputs'!$B$69 -> 1500 | J13: ='Model Inputs'!$B$69 -> 1500 | K13: ='Model Inputs'!$B$69 -> 1500 | L13: ='Model Inputs'!$B$69 -> 1500 | M13: ='Model Inputs'!$B$69 -> 1500 | N13: ='Model Inputs'!$C$69 -> 3000 | O13: ='Model Inputs'!$C$69 -> 3000 | P13: ='Model Inputs'!$C$69 -> 3000 | Q13: ='Model Inputs'!$C$69 -> 3000 | R13: ='Model Inputs'!$C$69 -> 3000 | S13: ='Model Inputs'!$C$69 -> 3000 | T13: ='Model Inputs'!$C$69 -> 3000 | U13: ='Model Inputs'!$C$69 -> 3000 | ... Y13: ='Model Inputs'!$C$69 -> 3000 | Z13: ='Model Inputs'!$D$69 -> 5000 | AA13: ='Model Inputs'!$D$69 -> 5000 | AB13: ='Model Inputs'!$D$69 -> 5000 | AC13: ='Model Inputs'!$D$69 -> 5000 | AD13: ='Model Inputs'!$D$69 -> 5000 | AE13: ='Model Inputs'!$D$69 -> 5000 | AF13: ='Model Inputs'!$D$69 -> 5000 | AG13: ='Model Inputs'!$D$69 -> 5000 | ... AK13: ='Model Inputs'!$D$69 -> 5000
A14: Blockchain RPC (Alchemy/Helius) | B14: 0 | C14: 0 | D14: 0 | E14: 0 | F14: 0 | G14: 0 | H14: 0 | I14: 0 | J14: 0 | K14: 0 | L14: 0 | M14: 0 | N14: 0 | O14: 0 | P14: 0 | Q14: ='Model Inputs'!$C$70 -> 249 | R14: ='Model Inputs'!$C$70 -> 249 | S14: ='Model Inputs'!$C$70 -> 249 | T14: ='Model Inputs'!$C$70 -> 249 | U14: ='Model Inputs'!$C$70 -> 249 | V14: ='Model Inputs'!$C$70 -> 249 | W14: ='Model Inputs'!$C$70 -> 249 | X14: ='Model Inputs'!$C$70 -> 249 | Y14: ='Model Inputs'!$C$70 -> 249 | Z14: ='Model Inputs'!$D$70 -> 499 | AA14: ='Model Inputs'!$D$70 -> 499 | AB14: ='Model Inputs'!$D$70 -> 499 | AC14: ='Model Inputs'!$D$70 -> 499 | AD14: ='Model Inputs'!$D$70 -> 499 | AE14: ='Model Inputs'!$D$70 -> 499 | AF14: ='Model Inputs'!$D$70 -> 499 | AG14: ='Model Inputs'!$D$70 -> 499 | ... AL14: ='Model Inputs'!$D$70 -> 499
A15: Monitoring | B15: 0 | C15: 0 | D15: 0 | E15: ='Model Inputs'!$B$71 -> 0 | F15: ='Model Inputs'!$B$71 -> 0 | G15: ='Model Inputs'!$B$71 -> 0 | H15: ='Model Inputs'!$B$71 -> 0 | I15: ='Model Inputs'!$B$71 -> 0 | J15: ='Model Inputs'!$B$71 -> 0 | K15: ='Model Inputs'!$B$71 -> 0 | L15: ='Model Inputs'!$B$71 -> 0 | M15: ='Model Inputs'!$B$71 -> 0 | N15: ='Model Inputs'!$C$71 -> 350 | O15: ='Model Inputs'!$C$71 -> 350 | P15: ='Model Inputs'!$C$71 -> 350 | Q15: ='Model Inputs'!$C$71 -> 350 | R15: ='Model Inputs'!$C$71 -> 350 | S15: ='Model Inputs'!$C$71 -> 350 | T15: ='Model Inputs'!$C$71 -> 350 | U15: ='Model Inputs'!$C$71 -> 350 | ... Y15: ='Model Inputs'!$C$71 -> 350 | Z15: ='Model Inputs'!$D$71 -> 600 | AA15: ='Model Inputs'!$D$71 -> 600 | AB15: ='Model Inputs'!$D$71 -> 600 | AC15: ='Model Inputs'!$D$71 -> 600 | AD15: ='Model Inputs'!$D$71 -> 600 | AE15: ='Model Inputs'!$D$71 -> 600 | AF15: ='Model Inputs'!$D$71 -> 600 | AG15: ='Model Inputs'!$D$71 -> 600 | ... AK15: ='Model Inputs'!$D$71 -> 600
A16: Transactional Email (SendGrid) | B16: 0 | C16: 0 | D16: 0 | E16: ='Model Inputs'!$B$73 -> 0 | F16: ='Model Inputs'!$B$73 -> 0 | G16: ='Model Inputs'!$B$73 -> 0 | H16: ='Model Inputs'!$B$73 -> 0 | I16: ='Model Inputs'!$B$73 -> 0 | J16: ='Model Inputs'!$B$73 -> 0 | K16: ='Model Inputs'!$B$73 -> 0 | L16: ='Model Inputs'!$B$73 -> 0 | M16: ='Model Inputs'!$B$73 -> 0 | N16: ='Model Inputs'!$C$73 -> 50 | O16: ='Model Inputs'!$C$73 -> 50 | P16: ='Model Inputs'!$C$73 -> 50 | Q16: ='Model Inputs'!$C$73 -> 50 | R16: ='Model Inputs'!$C$73 -> 50 | S16: ='Model Inputs'!$C$73 -> 50 | T16: ='Model Inputs'!$C$73 -> 50 | U16: ='Model Inputs'!$C$73 -> 50 | ... Y16: ='Model Inputs'!$C$73 -> 50 | Z16: ='Model Inputs'!$D$73 -> 90 | AA16: ='Model Inputs'!$D$73 -> 90 | AB16: ='Model Inputs'!$D$73 -> 90 | AC16: ='Model Inputs'!$D$73 -> 90 | AD16: ='Model Inputs'!$D$73 -> 90 | AE16: ='Model Inputs'!$D$73 -> 90 | AF16: ='Model Inputs'!$D$73 -> 90 | AG16: ='Model Inputs'!$D$73 -> 90 | ... AL16: ='Model Inputs'!$D$73 -> 90
A17: TRUE FIXED COSTS
A18: Base Compute | B18: 0 | C18: 0 | D18: 0 | E18: ='Model Inputs'!$B$76 -> 200 | F18: ='Model Inputs'!$B$76 -> 200 | G18: ='Model Inputs'!$B$76 -> 200 | H18: ='Model Inputs'!$B$76 -> 200 | I18: ='Model Inputs'!$B$76 -> 200 | J18: ='Model Inputs'!$B$76 -> 200 | K18: ='Model Inputs'!$B$76 -> 200 | L18: ='Model Inputs'!$B$76 -> 200 | M18: ='Model Inputs'!$B$76 -> 200 | N18: ='Model Inputs'!$C$76 -> 350 | O18: ='Model Inputs'!$C$76 -> 350 | P18: ='Model Inputs'!$C$76 -> 350 | Q18: ='Model Inputs'!$C$76 -> 350 | R18: ='Model Inputs'!$C$76 -> 350 | S18: ='Model Inputs'!$C$76 -> 350 | T18: ='Model Inputs'!$C$76 -> 350 | U18: ='Model Inputs'!$C$76 -> 350 | ... Y18: ='Model Inputs'!$C$76 -> 350 | Z18: ='Model Inputs'!$D$76 -> 500 | AA18: ='Model Inputs'!$D$76 -> 500 | AB18: ='Model Inputs'!$D$76 -> 500 | AC18: ='Model Inputs'!$D$76 -> 500 | AD18: ='Model Inputs'!$D$76 -> 500 | AE18: ='Model Inputs'!$D$76 -> 500 | AF18: ='Model Inputs'!$D$76 -> 500 | AG18: ='Model Inputs'!$D$76 -> 500 | ... AK18: ='Model Inputs'!$D$76 -> 500
A19: DR Infrastructure | B19: 0 | C19: 0 | D19: 0 | E19: ='Model Inputs'!$B$77 -> 200 | F19: ='Model Inputs'!$B$77 -> 200 | G19: ='Model Inputs'!$B$77 -> 200 | H19: ='Model Inputs'!$B$77 -> 200 | I19: ='Model Inputs'!$B$77 -> 200 | J19: ='Model Inputs'!$B$77 -> 200 | K19: ='Model Inputs'!$B$77 -> 200 | L19: ='Model Inputs'!$B$77 -> 200 | M19: ='Model Inputs'!$B$77 -> 200 | N19: ='Model Inputs'!$C$77 -> 300 | O19: ='Model Inputs'!$C$77 -> 300 | P19: ='Model Inputs'!$C$77 -> 300 | Q19: ='Model Inputs'!$C$77 -> 300 | R19: ='Model Inputs'!$C$77 -> 300 | S19: ='Model Inputs'!$C$77 -> 300 | T19: ='Model Inputs'!$C$77 -> 300 | U19: ='Model Inputs'!$C$77 -> 300 | ... Y19: ='Model Inputs'!$C$77 -> 300 | Z19: ='Model Inputs'!$D$77 -> 400 | AA19: ='Model Inputs'!$D$77 -> 400 | AB19: ='Model Inputs'!$D$77 -> 400 | AC19: ='Model Inputs'!$D$77 -> 400 | AD19: ='Model Inputs'!$D$77 -> 400 | AE19: ='Model Inputs'!$D$77 -> 400 | AF19: ='Model Inputs'!$D$77 -> 400 | AG19: ='Model Inputs'!$D$77 -> 400 | ... AK19: ='Model Inputs'!$D$77 -> 400
A20: Total COGS | B20: =SUM(B5:B11)+SUM(B13:B16)+SUM(B18:B19) -> 0 | C20: =SUM(C5:C11)+SUM(C13:C16)+SUM(C18:C19) -> 0 | D20: =SUM(D5:D11)+SUM(D13:D16)+SUM(D18:D19) -> 0 | E20: =SUM(E5:E11)+SUM(E13:E16)+SUM(E18:E19) -> 3193.93 | F20: =SUM(F5:F11)+SUM(F13:F16)+SUM(F18:F19) -> 3943.7156 | G20: =SUM(G5:G11)+SUM(G13:G16)+SUM(G18:G19) -> 5122.0752 | H20: =SUM(H5:H11)+SUM(H13:H16)+SUM(H18:H19) -> 6526.465 | I20: =SUM(I5:I11)+SUM(I13:I16)+SUM(I18:I19) -> 7931.5 | ... AK20: =SUM(AK5:AK11)+SUM(AK13:AK16)+SUM(AK18:AK19) -> 88735.079
A21: MARGIN ANALYSIS
A22: Gross Profit | B22: ='Revenue Model'!B$31-B20 -> 0 | C22: ='Revenue Model'!C$31-C20 -> 0 | D22: ='Revenue Model'!D$31-D20 -> 0 | E22: ='Revenue Model'!E$31-E20 -> 3956.07 | F22: ='Revenue Model'!F$31-F20 -> 6765.7878 | G22: ='Revenue Model'!G$31-G20 -> 12777.76 | H22: ='Revenue Model'!H$31-H20 -> 18926.121 | I22: ='Revenue Model'!I$31-I20 -> 25250.914 | ... AK22: ='Revenue Model'!AK$31-AK20 -> 627754.69 | AL22: ='Revenue Model'!AL$31-AL$18 -> 675903 | AM22: ='Revenue Model'!AM$31-AM$18 -> 0
A23: Gross Margin % | B23: =IF('Revenue Model'!B$31>0,B22/'Revenue Model'!B$31,0) -> 0 | C23: =IF('Revenue Model'!C$31>0,C22/'Revenue Model'!C$31,0) -> 0 | D23: =IF('Revenue Model'!D$31>0,D22/'Revenue Model'!D$31,0) -> 0 | E23: =IF('Revenue Model'!E$31>0,E22/'Revenue Model'!E$31,0) -> 0.5532965 | F23: =IF('Revenue Model'!F$31>0,F22/'Revenue Model'!F$31,0) -> 0.63175551 | G23: =IF('Revenue Model'!G$31>0,G22/'Revenue Model'!G$31,0) -> 0.71384791 | H23: =IF('Revenue Model'!H$31>0,H22/'Revenue Model'!H$31,0) -> 0.74358343 | I23: =IF('Revenue Model'!I$31>0,I22/'Revenue Model'!I$31,0) -> 0.76097278 | ... AK23: =IF('Revenue Model'!AK$31>0,AK22/'Revenue Model'!AK$31,0) -> 0.87615304 | AL23: =IF('Revenue Model'!AL$31>0,AL$20/'Revenue Model'!AL$31,0) -> 0 | AM23: =IF('Revenue Model'!AM$31>0,AM$20/'Revenue Model'!AM$31,0) -> 0
A26: MERCURY BANKING STARTUP PERKS - INFRASTRUCTURE DISCOUNTS
A28: Solution | B28: Category | C28: List Price | D28: Our Price | E28: Annual Savings | F28: Discount | G28: Notes
A29: Filebase | B29: IPFS Storage | C29: $1,200 | D29: $0 | E29: $1,200 | F29: 100% | G29: 12-month credits via Mercury Perks
A30: Datadog | B30: Monitoring | C30: $1,800 | D30: $0 | E30: $1,800 | F30: 100% | G30: Startup program (Y1 free)
A31: Alchemy | B31: Blockchain RPC | C31: $2,500 | D31: $0 | E31: $2,500 | F31: 100% | G31: Early Stage program (Y1-Y3 tiered)
A32: SendGrid | B32: Email | C32: $600 | D32: $0 | E32: $600 | F32: 100% | G32: 12-month credits (backup/reserve)
A33: TOTAL Y1 SAVINGS | E33: $6,100 | G33: Primary RPC - no discount available
A34: Stripe | B34: Payments | C34: 2.9% | D34: 2.9% | E34: $0 | F34: 0% | G34: Standard rate - no startup discount
A35: INFRASTRUCTURE STACK SUMMARY (Monthly)
A37: Component | B37: Solution | C37: Y1 | D37: Y2 | E37: Y3 | F37: Notes
A38: Storage Infrastructure | B38: Filebase | C38: $1,500 | D38: $3,000 | E38: $5,000 | F38: Mercury credit Y1
A39: Blockchain RPC | B39: Alchemy → Helius | C39: $0 | D39: $249 | E39: $499 | F39: Alchemy credit covers Y1
A40: Monitoring | B40: Datadog | C40: $0 | D40: $350 | E40: $600 | F40: Mercury credit Y1
A41: Transactional Email | B41: SendGrid | C41: $0 | D41: $50 | E41: $90 | F41: Free tier Y1 | G41: Justification
A42: Base Compute | B42: Vercel/AWS | C42: $200 | D42: $350 | E42: $500 | G42: Dedicated IPFS gateways, 99.9% SLA
A43: DR Infrastructure | B43: Multi-region | C43: $200 | D43: $300 | E43: $400 | G43: Solana-optimized, staked connections
A44: MONTHLY TOTAL | C44: $1,900 | D44: $4,299 | E44: $7,089 | F44: Startup → Pro | G44: APM, logs, infrastructure metrics
A46: Notes: | F46: Standard | G46: PCI compliant, subscription billing
A47: • Alchemy $2,500 credit replaces Helius in Y1 (both are Solana RPC providers)
A48: • SOL gas fees (~$0.01/seat) must be paid in SOL regardless of RPC provider
A49: • Blockchain Gas costs are negligible (<$100/mo even at 10K seats)
A50: • All startup credits accessed via Mercury Banking partnership
A51: Note: Startup discounts accessed through Mercury Banking startup perks program. Credits and discounts verified as of December 2024.

Sheet Staffing Plan
A1: STAFFING PLAN - 36-MONTH DETAIL
A3: Role | B3: Dept | C3: Annual Salary | D3: Start Month | E3: Loading Type | F3: Y1M1 | G3: Y1M2 | H3: Y1M3 | I3: Y1M4 | J3: Y1M5 | K3: Y1M6 | L3: Y1M7 | M3: Y1M8 | N3: Y1M9 | O3: Y1M10 | P3: Y1M11 | Q3: Y1M12 | R3: Y2M1 | S3: Y2M2 | T3: Y2M3 | U3: Y2M4 | V3: Y2M5 | W3: Y2M6 | X3: Y2M7 | Y3: Y2M8 | Z3: Y2M9 | AA3: Y2M10 | AB3: Y2M11 | AC3: Y2M12 | AD3: Y3M1 | AE3: Y3M2 | AF3: Y3M3 | AG3: Y3M4 | AH3: Y3M5 | AI3: Y3M6 | AJ3: Y3M7 | AK3: Y3M8 | AL3: Y3M9 | AM3: Y3M10 | AN3: Y3M11 | AO3: Y3M12
A4: CEO / Head of Sales | B4: Executive | C4: 90000 | D4: 1 | E4: founder | F4: =IF(1>=$D4,$C4/12,0) -> 7500 | G4: =IF(2>=$D4,$C4/12,0) -> 7500 | H4: =IF(3>=$D4,$C4/12,0) -> 7500 | I4: =IF(4>=$D4,$C4/12,0) -> 7500 | J4: =IF(5>=$D4,$C4/12,0) -> 7500 | K4: =IF(6>=$D4,$C4/12,0) -> 7500 | L4: =IF(7>=$D4,$C4/12,0) -> 7500 | M4: =IF(8>=$D4,$C4/12,0) -> 7500 | N4: =IF(9>=$D4,$C4/12,0) -> 7500 | O4: =IF(10>=$D4,$C4/12,0) -> 7500 | P4: =IF(11>=$D4,$C4/12,0) -> 7500 | Q4: =IF(12>=$D4,$C4/12,0) -> 7500 | R4: =IF(13>=$D4,$C4/12,0) -> 7500 | S4: =IF(14>=$D4,$C4/12,0) -> 7500 | T4: =IF(15>=$D4,$C4/12,0) -> 7500 | U4: =IF(16>=$D4,$C4/12,0) -> 7500 | V4: =IF(17>=$D4,$C4/12,0) -> 7500 | W4: =IF(18>=$D4,$C4/12,0) -> 7500 | X4: =IF(19>=$D4,$C4/12,0) -> 7500 | Y4: =IF(20>=$D4,$C4/12,0) -> 7500 | Z4: =IF(21>=$D4,$C4/12,0) -> 7500 | AA4: =IF(22>=$D4,$C4/12,0) -> 7500 | AB4: =IF(23>=$D4,$C4/12,0) -> 7500 | AC4: =IF(24>=$D4,$C4/12,0) -> 7500 | AD4: =IF(25>=$D4,$C4/12,0) -> 7500 | AE4: =IF(26>=$D4,$C4/12,0) -> 7500 | AF4: =IF(27>=$D4,$C4/12,0) -> 7500 | AG4: =IF(28>=$D4,$C4/12,0) -> 7500 | AH4: =IF(29>=$D4,$C4/12,0) -> 7500 | AI4: =IF(30>=$D4,$C4/12,0) -> 7500 | AJ4: =IF(31>=$D4,$C4/12,0) -> 7500 | AK4: =IF(32>=$D4,$C4/12,0) -> 7500 | AL4: =IF(33>=$D4,$C4/12,0) -> 7500 | AM4: =IF(34>=$D4,$C4/12,0) -> 7500 | AN4: =IF(35>=$D4,$C4/12,0) -> 7500 | AO4: =IF(36>=$D4,$C4/12,0) -> 7500
A5: CTO / Sr. Full Stack | B5: Engineering | C5: 90000 | D5: 1 | E5: founder | F5: =IF(1>=$D5,$C5/12,0) -> 7500 | G5: =IF(2>=$D5,$C5/12,0) -> 7500 | H5: =IF(3>=$D5,$C5/12,0) -> 7500 | I5: =IF(4>=$D5,$C5/12,0) -> 7500 | J5: =IF(5>=$D5,$C5/12,0) -> 7500 | K5: =IF(6>=$D5,$C5/12,0) -> 7500 | L5: =IF(7>=$D5,$C5/12,0) -> 7500 | M5: =IF(8>=$D5,$C5/12,0) -> 7500 | N5: =IF(9>=$D5,$C5/12,0) -> 7500 | O5: =IF(10>=$D5,$C5/12,0) -> 7500 | P5: =IF(11>=$D5,$C5/12,0) -> 7500 | Q5: =IF(12>=$D5,$C5/12,0) -> 7500 | R5: =IF(13>=$D5,$C5/12,0) -> 7500 | S5: =IF(14>=$D5,$C5/12,0) -> 7500 | T5: =IF(15>=$D5,$C5/12,0) -> 7500 | U5: =IF(16>=$D5,$C5/12,0) -> 7500 | V5: =IF(17>=$D5,$C5/12,0) -> 7500 | W5: =IF(18>=$D5,$C5/12,0) -> 7500 | X5: =IF(19>=$D5,$C5/12,0) -> 7500 | Y5: =IF(20>=$D5,$C5/12,0) -> 7500 | Z5: =IF(21>=$D5,$C5/12,0) -> 7500 | AA5: =IF(22>=$D5,$C5/12,0) -> 7500 | AB5: =IF(23>=$D5,$C5/12,0) -> 7500 | AC5: =IF(24>=$D5,$C5/12,0) -> 7500 | AD5: =IF(25>=$D5,$C5/12,0) -> 7500 | AE5: =IF(26>=$D5,$C5/12,0) -> 7500 | AF5: =IF(27>=$D5,$C5/12,0) -> 7500 | AG5: =IF(28>=$D5,$C5/12,0) -> 7500 | AH5: =IF(29>=$D5,$C5/12,0) -> 7500 | AI5: =IF(30>=$D5,$C5/12,0) -> 7500 | AJ5: =IF(31>=$D5,$C5/12,0) -> 7500 | AK5: =IF(32>=$D5,$C5/12,0) -> 7500 | AL5: =IF(33>=$D5,$C5/12,0) -> 7500 | AM5: =IF(34>=$D5,$C5/12,0) -> 7500 | AN5: =IF(35>=$D5,$C5/12,0) -> 7500 | AO5: =IF(36>=$D5,$C5/12,0) -> 7500
A6: Sr. Protocol Engineer | B6: Engineering | C6: 90000 | D6: 1 | E6: intlContractor | F6: =IF(1>=$D6,$C6/12,0) -> 7500 | G6: =IF(2>=$D6,$C6/12,0) -> 7500 | H6: =IF(3>=$D6,$C6/12,0) -> 7500 | I6: =IF(4>=$D6,$C6/12,0) -> 7500 | J6: =IF(5>=$D6,$C6/12,0) -> 7500 | K6: =IF(6>=$D6,$C6/12,0) -> 7500 | L6: =IF(7>=$D6,$C6/12,0) -> 7500 | M6: =IF(8>=$D6,$C6/12,0) -> 7500 | N6: =IF(9>=$D6,$C6/12,0) -> 7500 | O6: =IF(10>=$D6,$C6/12,0) -> 7500 | P6: =IF(11>=$D6,$C6/12,0) -> 7500 | Q6: =IF(12>=$D6,$C6/12,0) -> 7500 | R6: =IF(13>=$D6,$C6/12,0) -> 7500 | S6: =IF(14>=$D6,$C6/12,0) -> 7500 | T6: =IF(15>=$D6,$C6/12,0) -> 7500 | U6: =IF(16>=$D6,$C6/12,0) -> 7500 | V6: =IF(17>=$D6,$C6/12,0) -> 7500 | W6: =IF(18>=$D6,$C6/12,0) -> 7500 | X6: =IF(19>=$D6,$C6/12,0) -> 7500 | Y6: =IF(20>=$D6,$C6/12,0) -> 7500 | Z6: =IF(21>=$D6,$C6/12,0) -> 7500 | AA6: =IF(22>=$D6,$C6/12,0) -> 7500 | AB6: =IF(23>=$D6,$C6/12,0) -> 7500 | AC6: =IF(24>=$D6,$C6/12,0) -> 7500 | AD6: =IF(25>=$D6,$C6/12,0) -> 7500 | AE6: =IF(26>=$D6,$C6/12,0) -> 7500 | AF6: =IF(27>=$D6,$C6/12,0) -> 7500 | AG6: =IF(28>=$D6,$C6/12,0) -> 7500 | AH6: =IF(29>=$D6,$C6/12,0) -> 7500 | AI6: =IF(30>=$D6,$C6/12,0) -> 7500 | AJ6: =IF(31>=$D6,$C6/12,0) -> 7500 | AK6: =IF(32>=$D6,$C6/12,0) -> 7500 | AL6: =IF(33>=$D6,$C6/12,0) -> 7500 | AM6: =IF(34>=$D6,$C6/12,0) -> 7500 | AN6: =IF(35>=$D6,$C6/12,0) -> 7500 | AO6: =IF(36>=$D6,$C6/12,0) -> 7500
A7: Backend Security Eng | B7: Engineering | C7: 80000 | D7: 8 | E7: intlContractor | F7: =IF(1>=$D7,$C7/12,0) -> 0 | G7: =IF(2>=$D7,$C7/12,0) -> 0 | H7: =IF(3>=$D7,$C7/12,0) -> 0 | I7: =IF(4>=$D7,$C7/12,0) -> 0 | J7: =IF(5>=$D7,$C7/12,0) -> 0 | K7: =IF(6>=$D7,$C7/12,0) -> 0 | L7: =IF(7>=$D7,$C7/12,0) -> 0 | M7: =IF(8>=$D7,$C7/12,0) -> 6666.6667 | N7: =IF(9>=$D7,$C7/12,0) -> 6666.6667 | O7: =IF(10>=$D7,$C7/12,0) -> 6666.6667 | P7: =IF(11>=$D7,$C7/12,0) -> 6666.6667 | Q7: =IF(12>=$D7,$C7/12,0) -> 6666.6667 | R7: =IF(13>=$D7,$C7/12,0) -> 6666.6667 | S7: =IF(14>=$D7,$C7/12,0) -> 6666.6667 | T7: =IF(15>=$D7,$C7/12,0) -> 6666.6667 | U7: =IF(16>=$D7,$C7/12,0) -> 6666.6667 | V7: =IF(17>=$D7,$C7/12,0) -> 6666.6667 | W7: =IF(18>=$D7,$C7/12,0) -> 6666.6667 | X7: =IF(19>=$D7,$C7/12,0) -> 6666.6667 | Y7: =IF(20>=$D7,$C7/12,0) -> 6666.6667 | Z7: =IF(21>=$D7,$C7/12,0) -> 6666.6667 | AA7: =IF(22>=$D7,$C7/12,0) -> 6666.6667 | AB7: =IF(23>=$D7,$C7/12,0) -> 6666.6667 | AC7: =IF(24>=$D7,$C7/12,0) -> 6666.6667 | AD7: =IF(25>=$D7,$C7/12,0) -> 6666.6667 | AE7: =IF(26>=$D7,$C7/12,0) -> 6666.6667 | AF7: =IF(27>=$D7,$C7/12,0) -> 6666.6667 | AG7: =IF(28>=$D7,$C7/12,0) -> 6666.6667 | AH7: =IF(29>=$D7,$C7/12,0) -> 6666.6667 | AI7: =IF(30>=$D7,$C7/12,0) -> 6666.6667 | AJ7: =IF(31>=$D7,$C7/12,0) -> 6666.6667 | AK7: =IF(32>=$D7,$C7/12,0) -> 6666.6667 | AL7: =IF(33>=$D7,$C7/12,0) -> 6666.6667 | AM7: =IF(34>=$D7,$C7/12,0) -> 6666.6667 | AN7: =IF(35>=$D7,$C7/12,0) -> 6666.6667 | AO7: =IF(36>=$D7,$C7/12,0) -> 6666.6667
A8: Developer Advocate | B8: Marketing | C8: 85000 | D8: 99 | E8: us | F8: =IF(1>=$D8,$C8/12,0) -> 0 | G8: =IF(2>=$D8,$C8/12,0) -> 0 | H8: =IF(3>=$D8,$C8/12,0) -> 0 | I8: =IF(4>=$D8,$C8/12,0) -> 0 | J8: =IF(5>=$D8,$C8/12,0) -> 0 | K8: =IF(6>=$D8,$C8/12,0) -> 0 | L8: =IF(7>=$D8,$C8/12,0) -> 0 | M8: =IF(8>=$D8,$C8/12,0) -> 0 | N8: =IF(9>=$D8,$C8/12,0) -> 0 | O8: =IF(10>=$D8,$C8/12,0) -> 0 | P8: =IF(11>=$D8,$C8/12,0) -> 0 | Q8: =IF(12>=$D8,$C8/12,0) -> 0 | R8: =IF(13>=$D8,$C8/12,0) -> 0 | S8: =IF(14>=$D8,$C8/12,0) -> 0 | T8: =IF(15>=$D8,$C8/12,0) -> 0 | U8: =IF(16>=$D8,$C8/12,0) -> 0 | V8: =IF(17>=$D8,$C8/12,0) -> 0 | W8: =IF(18>=$D8,$C8/12,0) -> 0 | X8: =IF(19>=$D8,$C8/12,0) -> 0 | Y8: =IF(20>=$D8,$C8/12,0) -> 0 | Z8: =IF(21>=$D8,$C8/12,0) -> 0 | AA8: =IF(22>=$D8,$C8/12,0) -> 0 | AB8: =IF(23>=$D8,$C8/12,0) -> 0 | AC8: =IF(24>=$D8,$C8/12,0) -> 0 | AD8: =IF(25>=$D8,$C8/12,0) -> 0 | AE8: =IF(26>=$D8,$C8/12,0) -> 0 | AF8: =IF(27>=$D8,$C8/12,0) -> 0 | AG8: =IF(28>=$D8,$C8/12,0) -> 0 | AH8: =IF(29>=$D8,$C8/12,0) -> 0 | AI8: =IF(30>=$D8,$C8/12,0) -> 0 | AJ8: =IF(31>=$D8,$C8/12,0) -> 0 | AK8: =IF(32>=$D8,$C8/12,0) -> 0 | AL8: =IF(33>=$D8,$C8/12,0) -> 0 | AM8: =IF(34>=$D8,$C8/12,0) -> 0 | AN8: =IF(35>=$D8,$C8/12,0) -> 0 | AO8: =IF(36>=$D8,$C8/12,0) -> 0
A9: Customer Success Lead | B9: CS | C9: 65000 | D9: 10 | E9: us | F9: =IF(1>=$D9,$C9/12,0) -> 0 | G9: =IF(2>=$D9,$C9/12,0) -> 0 | H9: =IF(3>=$D9,$C9/12,0) -> 0 | I9: =IF(4>=$D9,$C9/12,0) -> 0 | J9: =IF(5>=$D9,$C9/12,0) -> 0 | K9: =IF(6>=$D9,$C9/12,0) -> 0 | L9: =IF(7>=$D9,$C9/12,0) -> 0 | M9: =IF(8>=$D9,$C9/12,0) -> 0 | N9: =IF(9>=$D9,$C9/12,0) -> 0 | O9: =IF(10>=$D9,$C9/12,0) -> 5416.6667 | P9: =IF(11>=$D9,$C9/12,0) -> 5416.6667 | Q9: =IF(12>=$D9,$C9/12,0) -> 5416.6667 | R9: =IF(13>=$D9,$C9/12,0) -> 5416.6667 | S9: =IF(14>=$D9,$C9/12,0) -> 5416.6667 | T9: =IF(15>=$D9,$C9/12,0) -> 5416.6667 | U9: =IF(16>=$D9,$C9/12,0) -> 5416.6667 | V9: =IF(17>=$D9,$C9/12,0) -> 5416.6667 | W9: =IF(18>=$D9,$C9/12,0) -> 5416.6667 | X9: =IF(19>=$D9,$C9/12,0) -> 5416.6667 | Y9: =IF(20>=$D9,$C9/12,0) -> 5416.6667 | Z9: =IF(21>=$D9,$C9/12,0) -> 5416.6667 | AA9: =IF(22>=$D9,$C9/12,0) -> 5416.6667 | AB9: =IF(23>=$D9,$C9/12,0) -> 5416.6667 | AC9: =IF(24>=$D9,$C9/12,0) -> 5416.6667 | AD9: =IF(25>=$D9,$C9/12,0) -> 5416.6667 | AE9: =IF(26>=$D9,$C9/12,0) -> 5416.6667 | AF9: =IF(27>=$D9,$C9/12,0) -> 5416.6667 | AG9: =IF(28>=$D9,$C9/12,0) -> 5416.6667 | AH9: =IF(29>=$D9,$C9/12,0) -> 5416.6667 | AI9: =IF(30>=$D9,$C9/12,0) -> 5416.6667 | AJ9: =IF(31>=$D9,$C9/12,0) -> 5416.6667 | AK9: =IF(32>=$D9,$C9/12,0) -> 5416.6667 | AL9: =IF(33>=$D9,$C9/12,0) -> 5416.6667 | AM9: =IF(34>=$D9,$C9/12,0) -> 5416.6667 | AN9: =IF(35>=$D9,$C9/12,0) -> 5416.6667 | AO9: =IF(36>=$D9,$C9/12,0) -> 5416.6667
A10: Account Executive 1 | B10: Sales | C10: 70000 | D10: 4 | E10: us | F10: =IF(1>=$D10,$C10/12,0) -> 0 | G10: =IF(2>=$D10,$C10/12,0) -> 0 | H10: =IF(3>=$D10,$C10/12,0) -> 0 | I10: =IF(4>=$D10,$C10/12,0) -> 5833.3333 | J10: =IF(5>=$D10,$C10/12,0) -> 5833.3333 | K10: =IF(6>=$D10,$C10/12,0) -> 5833.3333 | L10: =IF(7>=$D10,$C10/12,0) -> 5833.3333 | M10: =IF(8>=$D10,$C10/12,0) -> 5833.3333 | N10: =IF(9>=$D10,$C10/12,0) -> 5833.3333 | O10: =IF(10>=$D10,$C10/12,0) -> 5833.3333 | P10: =IF(11>=$D10,$C10/12,0) -> 5833.3333 | Q10: =IF(12>=$D10,$C10/12,0) -> 5833.3333 | R10: =IF(13>=$D10,$C10/12,0) -> 5833.3333 | S10: =IF(14>=$D10,$C10/12,0) -> 5833.3333 | T10: =IF(15>=$D10,$C10/12,0) -> 5833.3333 | U10: =IF(16>=$D10,$C10/12,0) -> 5833.3333 | V10: =IF(17>=$D10,$C10/12,0) -> 5833.3333 | W10: =IF(18>=$D10,$C10/12,0) -> 5833.3333 | X10: =IF(19>=$D10,$C10/12,0) -> 5833.3333 | Y10: =IF(20>=$D10,$C10/12,0) -> 5833.3333 | Z10: =IF(21>=$D10,$C10/12,0) -> 5833.3333 | AA10: =IF(22>=$D10,$C10/12,0) -> 5833.3333 | AB10: =IF(23>=$D10,$C10/12,0) -> 5833.3333 | AC10: =IF(24>=$D10,$C10/12,0) -> 5833.3333 | AD10: =IF(25>=$D10,$C10/12,0) -> 5833.3333 | AE10: =IF(26>=$D10,$C10/12,0) -> 5833.3333 | AF10: =IF(27>=$D10,$C10/12,0) -> 5833.3333 | AG10: =IF(28>=$D10,$C10/12,0) -> 5833.3333 | AH10: =IF(29>=$D10,$C10/12,0) -> 5833.3333 | AI10: =IF(30>=$D10,$C10/12,0) -> 5833.3333 | AJ10: =IF(31>=$D10,$C10/12,0) -> 5833.3333 | AK10: =IF(32>=$D10,$C10/12,0) -> 5833.3333 | AL10: =IF(33>=$D10,$C10/12,0) -> 5833.3333 | AM10: =IF(34>=$D10,$C10/12,0) -> 5833.3333 | AN10: =IF(35>=$D10,$C10/12,0) -> 5833.3333 | AO10: =IF(36>=$D10,$C10/12,0) -> 5833.3333
A11: SDR 1 | B11: Sales | C11: 50000 | D11: 16 | E11: us | F11: =IF(1>=$D11,$C11/12,0) -> 0 | G11: =IF(2>=$D11,$C11/12,0) -> 0 | H11: =IF(3>=$D11,$C11/12,0) -> 0 | I11: =IF(4>=$D11,$C11/12,0) -> 0 | J11: =IF(5>=$D11,$C11/12,0) -> 0 | K11: =IF(6>=$D11,$C11/12,0) -> 0 | L11: =IF(7>=$D11,$C11/12,0) -> 0 | M11: =IF(8>=$D11,$C11/12,0) -> 0 | N11: =IF(9>=$D11,$C11/12,0) -> 0 | O11: =IF(10>=$D11,$C11/12,0) -> 0 | P11: =IF(11>=$D11,$C11/12,0) -> 0 | Q11: =IF(12>=$D11,$C11/12,0) -> 0 | R11: =IF(13>=$D11,$C11/12,0) -> 0 | S11: =IF(14>=$D11,$C11/12,0) -> 0 | T11: =IF(15>=$D11,$C11/12,0) -> 0 | U11: =IF(16>=$D11,$C11/12,0) -> 4166.6667 | V11: =IF(17>=$D11,$C11/12,0) -> 4166.6667 | W11: =IF(18>=$D11,$C11/12,0) -> 4166.6667 | X11: =IF(19>=$D11,$C11/12,0) -> 4166.6667 | Y11: =IF(20>=$D11,$C11/12,0) -> 4166.6667 | Z11: =IF(21>=$D11,$C11/12,0) -> 4166.6667 | AA11: =IF(22>=$D11,$C11/12,0) -> 4166.6667 | AB11: =IF(23>=$D11,$C11/12,0) -> 4166.6667 | AC11: =IF(24>=$D11,$C11/12,0) -> 4166.6667 | AD11: =IF(25>=$D11,$C11/12,0) -> 4166.6667 | AE11: =IF(26>=$D11,$C11/12,0) -> 4166.6667 | AF11: =IF(27>=$D11,$C11/12,0) -> 4166.6667 | AG11: =IF(28>=$D11,$C11/12,0) -> 4166.6667 | AH11: =IF(29>=$D11,$C11/12,0) -> 4166.6667 | AI11: =IF(30>=$D11,$C11/12,0) -> 4166.6667 | AJ11: =IF(31>=$D11,$C11/12,0) -> 4166.6667 | AK11: =IF(32>=$D11,$C11/12,0) -> 4166.6667 | AL11: =IF(33>=$D11,$C11/12,0) -> 4166.6667 | AM11: =IF(34>=$D11,$C11/12,0) -> 4166.6667 | AN11: =IF(35>=$D11,$C11/12,0) -> 4166.6667 | AO11: =IF(36>=$D11,$C11/12,0) -> 4166.6667
A12: Frontend Engineer | B12: Engineering | C12: 78000 | D12: 14 | E12: intlContractor | F12: =IF(1>=$D12,$C12/12,0) -> 0 | G12: =IF(2>=$D12,$C12/12,0) -> 0 | H12: =IF(3>=$D12,$C12/12,0) -> 0 | I12: =IF(4>=$D12,$C12/12,0) -> 0 | J12: =IF(5>=$D12,$C12/12,0) -> 0 | K12: =IF(6>=$D12,$C12/12,0) -> 0 | L12: =IF(7>=$D12,$C12/12,0) -> 0 | M12: =IF(8>=$D12,$C12/12,0) -> 0 | N12: =IF(9>=$D12,$C12/12,0) -> 0 | O12: =IF(10>=$D12,$C12/12,0) -> 0 | P12: =IF(11>=$D12,$C12/12,0) -> 0 | Q12: =IF(12>=$D12,$C12/12,0) -> 0 | R12: =IF(13>=$D12,$C12/12,0) -> 0 | S12: =IF(14>=$D12,$C12/12,0) -> 6500 | T12: =IF(15>=$D12,$C12/12,0) -> 6500 | U12: =IF(16>=$D12,$C12/12,0) -> 6500 | V12: =IF(17>=$D12,$C12/12,0) -> 6500 | W12: =IF(18>=$D12,$C12/12,0) -> 6500 | X12: =IF(19>=$D12,$C12/12,0) -> 6500 | Y12: =IF(20>=$D12,$C12/12,0) -> 6500 | Z12: =IF(21>=$D12,$C12/12,0) -> 6500 | AA12: =IF(22>=$D12,$C12/12,0) -> 6500 | AB12: =IF(23>=$D12,$C12/12,0) -> 6500 | AC12: =IF(24>=$D12,$C12/12,0) -> 6500 | AD12: =IF(25>=$D12,$C12/12,0) -> 6500 | AE12: =IF(26>=$D12,$C12/12,0) -> 6500 | AF12: =IF(27>=$D12,$C12/12,0) -> 6500 | AG12: =IF(28>=$D12,$C12/12,0) -> 6500 | AH12: =IF(29>=$D12,$C12/12,0) -> 6500 | AI12: =IF(30>=$D12,$C12/12,0) -> 6500 | AJ12: =IF(31>=$D12,$C12/12,0) -> 6500 | AK12: =IF(32>=$D12,$C12/12,0) -> 6500 | AL12: =IF(33>=$D12,$C12/12,0) -> 6500 | AM12: =IF(34>=$D12,$C12/12,0) -> 6500 | AN12: =IF(35>=$D12,$C12/12,0) -> 6500 | AO12: =IF(36>=$D12,$C12/12,0) -> 6500
A13: Account Executive 2 | B13: Sales | C13: 65000 | D13: 16 | E13: us | F13: =IF(1>=$D13,$C13/12,0) -> 0 | G13: =IF(2>=$D13,$C13/12,0) -> 0 | H13: =IF(3>=$D13,$C13/12,0) -> 0 | I13: =IF(4>=$D13,$C13/12,0) -> 0 | J13: =IF(5>=$D13,$C13/12,0) -> 0 | K13: =IF(6>=$D13,$C13/12,0) -> 0 | L13: =IF(7>=$D13,$C13/12,0) -> 0 | M13: =IF(8>=$D13,$C13/12,0) -> 0 | N13: =IF(9>=$D13,$C13/12,0) -> 0 | O13: =IF(10>=$D13,$C13/12,0) -> 0 | P13: =IF(11>=$D13,$C13/12,0) -> 0 | Q13: =IF(12>=$D13,$C13/12,0) -> 0 | R13: =IF(13>=$D13,$C13/12,0) -> 0 | S13: =IF(14>=$D13,$C13/12,0) -> 0 | T13: =IF(15>=$D13,$C13/12,0) -> 0 | U13: =IF(16>=$D13,$C13/12,0) -> 5416.6667 | V13: =IF(17>=$D13,$C13/12,0) -> 5416.6667 | W13: =IF(18>=$D13,$C13/12,0) -> 5416.6667 | X13: =IF(19>=$D13,$C13/12,0) -> 5416.6667 | Y13: =IF(20>=$D13,$C13/12,0) -> 5416.6667 | Z13: =IF(21>=$D13,$C13/12,0) -> 5416.6667 | AA13: =IF(22>=$D13,$C13/12,0) -> 5416.6667 | AB13: =IF(23>=$D13,$C13/12,0) -> 5416.6667 | AC13: =IF(24>=$D13,$C13/12,0) -> 5416.6667 | AD13: =IF(25>=$D13,$C13/12,0) -> 5416.6667 | AE13: =IF(26>=$D13,$C13/12,0) -> 5416.6667 | AF13: =IF(27>=$D13,$C13/12,0) -> 5416.6667 | AG13: =IF(28>=$D13,$C13/12,0) -> 5416.6667 | AH13: =IF(29>=$D13,$C13/12,0) -> 5416.6667 | AI13: =IF(30>=$D13,$C13/12,0) -> 5416.6667 | AJ13: =IF(31>=$D13,$C13/12,0) -> 5416.6667 | AK13: =IF(32>=$D13,$C13/12,0) -> 5416.6667 | AL13: =IF(33>=$D13,$C13/12,0) -> 5416.6667 | AM13: =IF(34>=$D13,$C13/12,0) -> 5416.6667 | AN13: =IF(35>=$D13,$C13/12,0) -> 5416.6667 | AO13: =IF(36>=$D13,$C13/12,0) -> 5416.6667
A14: Head of Sales | B14: Executive | C14: 160000 | D14: 99 | E14: us | F14: =IF(1>=$D14,$C14/12,0) -> 0 | G14: =IF(2>=$D14,$C14/12,0) -> 0 | H14: =IF(3>=$D14,$C14/12,0) -> 0 | I14: =IF(4>=$D14,$C14/12,0) -> 0 | J14: =IF(5>=$D14,$C14/12,0) -> 0 | K14: =IF(6>=$D14,$C14/12,0) -> 0 | L14: =IF(7>=$D14,$C14/12,0) -> 0 | M14: =IF(8>=$D14,$C14/12,0) -> 0 | N14: =IF(9>=$D14,$C14/12,0) -> 0 | O14: =IF(10>=$D14,$C14/12,0) -> 0 | P14: =IF(11>=$D14,$C14/12,0) -> 0 | Q14: =IF(12>=$D14,$C14/12,0) -> 0 | R14: =IF(13>=$D14,$C14/12,0) -> 0 | S14: =IF(14>=$D14,$C14/12,0) -> 0 | T14: =IF(15>=$D14,$C14/12,0) -> 0 | U14: =IF(16>=$D14,$C14/12,0) -> 0 | V14: =IF(17>=$D14,$C14/12,0) -> 0 | W14: =IF(18>=$D14,$C14/12,0) -> 0 | X14: =IF(19>=$D14,$C14/12,0) -> 0 | Y14: =IF(20>=$D14,$C14/12,0) -> 0 | Z14: =IF(21>=$D14,$C14/12,0) -> 0 | AA14: =IF(22>=$D14,$C14/12,0) -> 0 | AB14: =IF(23>=$D14,$C14/12,0) -> 0 | AC14: =IF(24>=$D14,$C14/12,0) -> 0 | AD14: =IF(25>=$D14,$C14/12,0) -> 0 | AE14: =IF(26>=$D14,$C14/12,0) -> 0 | AF14: =IF(27>=$D14,$C14/12,0) -> 0 | AG14: =IF(28>=$D14,$C14/12,0) -> 0 | AH14: =IF(29>=$D14,$C14/12,0) -> 0 | AI14: =IF(30>=$D14,$C14/12,0) -> 0 | AJ14: =IF(31>=$D14,$C14/12,0) -> 0 | AK14: =IF(32>=$D14,$C14/12,0) -> 0 | AL14: =IF(33>=$D14,$C14/12,0) -> 0 | AM14: =IF(34>=$D14,$C14/12,0) -> 0 | AN14: =IF(35>=$D14,$C14/12,0) -> 0 | AO14: =IF(36>=$D14,$C14/12,0) -> 0
A15: Senior DevOps/SRE | B15: Engineering | C15: 95000 | D15: 18 | E15: intlContractor | F15: =IF(1>=$D15,$C15/12,0) -> 0 | G15: =IF(2>=$D15,$C15/12,0) -> 0 | H15: =IF(3>=$D15,$C15/12,0) -> 0 | I15: =IF(4>=$D15,$C15/12,0) -> 0 | J15: =IF(5>=$D15,$C15/12,0) -> 0 | K15: =IF(6>=$D15,$C15/12,0) -> 0 | L15: =IF(7>=$D15,$C15/12,0) -> 0 | M15: =IF(8>=$D15,$C15/12,0) -> 0 | N15: =IF(9>=$D15,$C15/12,0) -> 0 | O15: =IF(10>=$D15,$C15/12,0) -> 0 | P15: =IF(11>=$D15,$C15/12,0) -> 0 | Q15: =IF(12>=$D15,$C15/12,0) -> 0 | R15: =IF(13>=$D15,$C15/12,0) -> 0 | S15: =IF(14>=$D15,$C15/12,0) -> 0 | T15: =IF(15>=$D15,$C15/12,0) -> 0 | U15: =IF(16>=$D15,$C15/12,0) -> 0 | V15: =IF(17>=$D15,$C15/12,0) -> 0 | W15: =IF(18>=$D15,$C15/12,0) -> 7916.6667 | X15: =IF(19>=$D15,$C15/12,0) -> 7916.6667 | Y15: =IF(20>=$D15,$C15/12,0) -> 7916.6667 | Z15: =IF(21>=$D15,$C15/12,0) -> 7916.6667 | AA15: =IF(22>=$D15,$C15/12,0) -> 7916.6667 | AB15: =IF(23>=$D15,$C15/12,0) -> 7916.6667 | AC15: =IF(24>=$D15,$C15/12,0) -> 7916.6667 | AD15: =IF(25>=$D15,$C15/12,0) -> 7916.6667 | AE15: =IF(26>=$D15,$C15/12,0) -> 7916.6667 | AF15: =IF(27>=$D15,$C15/12,0) -> 7916.6667 | AG15: =IF(28>=$D15,$C15/12,0) -> 7916.6667 | AH15: =IF(29>=$D15,$C15/12,0) -> 7916.6667 | AI15: =IF(30>=$D15,$C15/12,0) -> 7916.6667 | AJ15: =IF(31>=$D15,$C15/12,0) -> 7916.6667 | AK15: =IF(32>=$D15,$C15/12,0) -> 7916.6667 | AL15: =IF(33>=$D15,$C15/12,0) -> 7916.6667 | AM15: =IF(34>=$D15,$C15/12,0) -> 7916.6667 | AN15: =IF(35>=$D15,$C15/12,0) -> 7916.6667 | AO15: =IF(36>=$D15,$C15/12,0) -> 7916.6667
... A28: Technical Recruiter | B28: Ops | C28: 80000 | D28: 36 | E28: us | F28: =IF(1>=$D28,$C28/12,0) -> 0 | G28: =IF(2>=$D28,$C28/12,0) -> 0 | H28: =IF(3>=$D28,$C28/12,0) -> 0 | I28: =IF(4>=$D28,$C28/12,0) -> 0 | J28: =IF(5>=$D28,$C28/12,0) -> 0 | K28: =IF(6>=$D28,$C28/12,0) -> 0 | L28: =IF(7>=$D28,$C28/12,0) -> 0 | M28: =IF(8>=$D28,$C28/12,0) -> 0 | N28: =IF(9>=$D28,$C28/12,0) -> 0 | O28: =IF(10>=$D28,$C28/12,0) -> 0 | P28: =IF(11>=$D28,$C28/12,0) -> 0 | Q28: =IF(12>=$D28,$C28/12,0) -> 0 | R28: =IF(13>=$D28,$C28/12,0) -> 0 | S28: =IF(14>=$D28,$C28/12,0) -> 0 | T28: =IF(15>=$D28,$C28/12,0) -> 0 | U28: =IF(16>=$D28,$C28/12,0) -> 0 | V28: =IF(17>=$D28,$C28/12,0) -> 0 | W28: =IF(18>=$D28,$C28/12,0) -> 0 | X28: =IF(19>=$D28,$C28/12,0) -> 0 | Y28: =IF(20>=$D28,$C28/12,0) -> 0 | Z28: =IF(21>=$D28,$C28/12,0) -> 0 | AA28: =IF(22>=$D28,$C28/12,0) -> 0 | AB28: =IF(23>=$D28,$C28/12,0) -> 0 | AC28: =IF(24>=$D28,$C28/12,0) -> 0 | AD28: =IF(25>=$D28,$C28/12,0) -> 0 | AE28: =IF(26>=$D28,$C28/12,0) -> 0 | AF28: =IF(27>=$D28,$C28/12,0) -> 0 | AG28: =IF(28>=$D28,$C28/12,0) -> 0 | AH28: =IF(29>=$D28,$C28/12,0) -> 0 | AI28: =IF(30>=$D28,$C28/12,0) -> 0 | AJ28: =IF(31>=$D28,$C28/12,0) -> 0 | AK28: =IF(32>=$D28,$C28/12,0) -> 0 | AL28: =IF(33>=$D28,$C28/12,0) -> 0 | AM28: =IF(34>=$D28,$C28/12,0) -> 0 | AN28: =IF(35>=$D28,$C28/12,0) -> 0 | AO28: =IF(36>=$D28,$C28/12,0) -> 6666.6667
A29: SALES CAPACITY METRICS
A30: Active AEs | B30: - | C30: - | D30: - | E30: - | F30: =IF(1>=$D$10,1,0)+IF(1>=$D$13,1,0)+IF(1>=$D$23,1,0) -> 0 | G30: =IF(2>=$D$10,1,0)+IF(2>=$D$13,1,0)+IF(2>=$D$23,1,0) -> 0 | H30: =IF(3>=$D$10,1,0)+IF(3>=$D$13,1,0)+IF(3>=$D$23,1,0) -> 0 | I30: =IF(4>=$D$10,1,0)+IF(4>=$D$13,1,0)+IF(4>=$D$23,1,0) -> 1 | J30: =IF(5>=$D$10,1,0)+IF(5>=$D$13,1,0)+IF(5>=$D$23,1,0) -> 1 | K30: =IF(6>=$D$10,1,0)+IF(6>=$D$13,1,0)+IF(6>=$D$23,1,0) -> 1 | L30: =IF(7>=$D$10,1,0)+IF(7>=$D$13,1,0)+IF(7>=$D$23,1,0) -> 1 | M30: =IF(8>=$D$10,1,0)+IF(8>=$D$13,1,0)+IF(8>=$D$23,1,0) -> 1 | N30: =IF(9>=$D$10,1,0)+IF(9>=$D$13,1,0)+IF(9>=$D$23,1,0) -> 1 | O30: =IF(10>=$D$10,1,0)+IF(10>=$D$13,1,0)+IF(10>=$D$23,1,0) -> 1 | P30: =IF(11>=$D$10,1,0)+IF(11>=$D$13,1,0)+IF(11>=$D$23,1,0) -> 1 | Q30: =IF(12>=$D$10,1,0)+IF(12>=$D$13,1,0)+IF(12>=$D$23,1,0) -> 1 | R30: =IF(13>=$D$10,1,0)+IF(13>=$D$13,1,0)+IF(13>=$D$23,1,0) -> 1 | S30: =IF(14>=$D$10,1,0)+IF(14>=$D$13,1,0)+IF(14>=$D$23,1,0) -> 1 | T30: =IF(15>=$D$10,1,0)+IF(15>=$D$13,1,0)+IF(15>=$D$23,1,0) -> 1 | U30: =IF(16>=$D$10,1,0)+IF(16>=$D$13,1,0)+IF(16>=$D$23,1,0) -> 2 | V30: =IF(17>=$D$10,1,0)+IF(17>=$D$13,1,0)+IF(17>=$D$23,1,0) -> 2 | W30: =IF(18>=$D$10,1,0)+IF(18>=$D$13,1,0)+IF(18>=$D$23,1,0) -> 2 | X30: =IF(19>=$D$10,1,0)+IF(19>=$D$13,1,0)+IF(19>=$D$23,1,0) -> 2 | Y30: =IF(20>=$D$10,1,0)+IF(20>=$D$13,1,0)+IF(20>=$D$23,1,0) -> 2 | Z30: =IF(21>=$D$10,1,0)+IF(21>=$D$13,1,0)+IF(21>=$D$23,1,0) -> 2 | AA30: =IF(22>=$D$10,1,0)+IF(22>=$D$13,1,0)+IF(22>=$D$23,1,0) -> 2 | AB30: =IF(23>=$D$10,1,0)+IF(23>=$D$13,1,0)+IF(23>=$D$23,1,0) -> 2 | AC30: =IF(24>=$D$10,1,0)+IF(24>=$D$13,1,0)+IF(24>=$D$23,1,0) -> 2 | AD30: =IF(25>=$D$10,1,0)+IF(25>=$D$13,1,0)+IF(25>=$D$23,1,0) -> 2 | AE30: =IF(26>=$D$10,1,0)+IF(26>=$D$13,1,0)+IF(26>=$D$23,1,0) -> 2 | AF30: =IF(27>=$D$10,1,0)+IF(27>=$D$13,1,0)+IF(27>=$D$23,1,0) -> 3 | AG30: =IF(28>=$D$10,1,0)+IF(28>=$D$13,1,0)+IF(28>=$D$23,1,0) -> 3 | AH30: =IF(29>=$D$10,1,0)+IF(29>=$D$13,1,0)+IF(29>=$D$23,1,0) -> 3 | AI30: =IF(30>=$D$10,1,0)+IF(30>=$D$13,1,0)+IF(30>=$D$23,1,0) -> 3 | AJ30: =IF(31>=$D$10,1,0)+IF(31>=$D$13,1,0)+IF(31>=$D$23,1,0) -> 3 | AK30: =IF(32>=$D$10,1,0)+IF(32>=$D$13,1,0)+IF(32>=$D$23,1,0) -> 3 | AL30: =IF(33>=$D$10,1,0)+IF(33>=$D$13,1,0)+IF(33>=$D$23,1,0) -> 3 | AM30: =IF(34>=$D$10,1,0)+IF(34>=$D$13,1,0)+IF(34>=$D$23,1,0) -> 3 | AN30: =IF(35>=$D$10,1,0)+IF(35>=$D$13,1,0)+IF(35>=$D$23,1,0) -> 3 | AO30: =IF(36>=$D$10,1,0)+IF(36>=$D$13,1,0)+IF(36>=$D$23,1,0) -> 3
A31: Active SDRs | B31: - | C31: - | D31: - | E31: - | F31: =IF(1>=$D$11,1,0)+IF(1>=$D$24,1,0) -> 0 | G31: =IF(2>=$D$11,1,0)+IF(2>=$D$24,1,0) -> 0 | H31: =IF(3>=$D$11,1,0)+IF(3>=$D$24,1,0) -> 0 | I31: =IF(4>=$D$11,1,0)+IF(4>=$D$24,1,0) -> 0 | J31: =IF(5>=$D$11,1,0)+IF(5>=$D$24,1,0) -> 0 | K31: =IF(6>=$D$11,1,0)+IF(6>=$D$24,1,0) -> 0 | L31: =IF(7>=$D$11,1,0)+IF(7>=$D$24,1,0) -> 0 | M31: =IF(8>=$D$11,1,0)+IF(8>=$D$24,1,0) -> 0 | N31: =IF(9>=$D$11,1,0)+IF(9>=$D$24,1,0) -> 0 | O31: =IF(10>=$D$11,1,0)+IF(10>=$D$24,1,0) -> 0 | P31: =IF(11>=$D$11,1,0)+IF(11>=$D$24,1,0) -> 0 | Q31: =IF(12>=$D$11,1,0)+IF(12>=$D$24,1,0) -> 0 | R31: =IF(13>=$D$11,1,0)+IF(13>=$D$24,1,0) -> 0 | S31: =IF(14>=$D$11,1,0)+IF(14>=$D$24,1,0) -> 0 | T31: =IF(15>=$D$11,1,0)+IF(15>=$D$24,1,0) -> 0 | U31: =IF(16>=$D$11,1,0)+IF(16>=$D$24,1,0) -> 1 | V31: =IF(17>=$D$11,1,0)+IF(17>=$D$24,1,0) -> 1 | W31: =IF(18>=$D$11,1,0)+IF(18>=$D$24,1,0) -> 1 | X31: =IF(19>=$D$11,1,0)+IF(19>=$D$24,1,0) -> 1 | Y31: =IF(20>=$D$11,1,0)+IF(20>=$D$24,1,0) -> 1 | Z31: =IF(21>=$D$11,1,0)+IF(21>=$D$24,1,0) -> 1 | AA31: =IF(22>=$D$11,1,0)+IF(22>=$D$24,1,0) -> 1 | AB31: =IF(23>=$D$11,1,0)+IF(23>=$D$24,1,0) -> 1 | AC31: =IF(24>=$D$11,1,0)+IF(24>=$D$24,1,0) -> 1 | AD31: =IF(25>=$D$11,1,0)+IF(25>=$D$24,1,0) -> 1 | AE31: =IF(26>=$D$11,1,0)+IF(26>=$D$24,1,0) -> 1 | AF31: =IF(27>=$D$11,1,0)+IF(27>=$D$24,1,0) -> 2 | AG31: =IF(28>=$D$11,1,0)+IF(28>=$D$24,1,0) -> 2 | AH31: =IF(29>=$D$11,1,0)+IF(29>=$D$24,1,0) -> 2 | AI31: =IF(30>=$D$11,1,0)+IF(30>=$D$24,1,0) -> 2 | AJ31: =IF(31>=$D$11,1,0)+IF(31>=$D$24,1,0) -> 2 | AK31: =IF(32>=$D$11,1,0)+IF(32>=$D$24,1,0) -> 2 | AL31: =IF(33>=$D$11,1,0)+IF(33>=$D$24,1,0) -> 2 | AM31: =IF(34>=$D$11,1,0)+IF(34>=$D$24,1,0) -> 2 | AN31: =IF(35>=$D$11,1,0)+IF(35>=$D$24,1,0) -> 2 | AO31: =IF(36>=$D$11,1,0)+IF(36>=$D$24,1,0) -> 2
A32: Total Loaded Payroll | B32: - | C32: - | D32: - | E32: - | F32: =F4*1+F5*1+F6*1.05+F7*1.05+F8*1.25+F9*1.25+F10*1.25+F11*1.25+F12*1.05+F13*1.25+F14*1.25+F15*1.05+F16*1.25+F17*1.05+F18*1.25+F19*1.25+F20*1.25+F21*1.05+F22*1.05+F23*1.25+F24*1.25+F25*1.25+F26*1.05+F27*1.25+F28*1.25 -> 22875 | G32: =G4*1+G5*1+G6*1.05+G7*1.05+G8*1.25+G9*1.25+G10*1.25+G11*1.25+G12*1.05+G13*1.25+G14*1.25+G15*1.05+G16*1.25+G17*1.05+G18*1.25+G19*1.25+G20*1.25+G21*1.05+G22*1.05+G23*1.25+G24*1.25+G25*1.25+G26*1.05+G27*1.25+G28*1.25 -> 22875 | H32: =H4*1+H5*1+H6*1.05+H7*1.05+H8*1.25+H9*1.25+H10*1.25+H11*1.25+H12*1.05+H13*1.25+H14*1.25+H15*1.05+H16*1.25+H17*1.05+H18*1.25+H19*1.25+H20*1.25+H21*1.05+H22*1.05+H23*1.25+H24*1.25+H25*1.25+H26*1.05+H27*1.25+H28*1.25 -> 22875 | I32: =I4*1+I5*1+I6*1.05+I7*1.05+I8*1.25+I9*1.25+I10*1.25+I11*1.25+I12*1.05+I13*1.25+I14*1.25+I15*1.05+I16*1.25+I17*1.05+I18*1.25+I19*1.25+I20*1.25+I21*1.05+I22*1.05+I23*1.25+I24*1.25+I25*1.25+I26*1.05+I27*1.25+I28*1.25 -> 38708.333 | J32: =J4*1+J5*1+J6*1.05+J7*1.05+J8*1.25+J9*1.25+J10*1.25+J11*1.25+J12*1.05+J13*1.25+J14*1.25+J15*1.05+J16*1.25+J17*1.05+J18*1.25+J19*1.25+J20*1.25+J21*1.05+J22*1.05+J23*1.25+J24*1.25+J25*1.25+J26*1.05+J27*1.25+J28*1.25 -> 38708.333 | K32: =K4*1+K5*1+K6*1.05+K7*1.05+K8*1.25+K9*1.25+K10*1.25+K11*1.25+K12*1.05+K13*1.25+K14*1.25+K15*1.05+K16*1.25+K17*1.05+K18*1.25+K19*1.25+K20*1.25+K21*1.05+K22*1.05+K23*1.25+K24*1.25+K25*1.25+K26*1.05+K27*1.25+K28*1.25 -> 38708.333 | L32: =L4*1+L5*1+L6*1.05+L7*1.05+L8*1.25+L9*1.25+L10*1.25+L11*1.25+L12*1.05+L13*1.25+L14*1.25+L15*1.05+L16*1.25+L17*1.05+L18*1.25+L19*1.25+L20*1.25+L21*1.05+L22*1.05+L23*1.25+L24*1.25+L25*1.25+L26*1.05+L27*1.25+L28*1.25 -> 38708.333 | M32: =M4*1+M5*1+M6*1.05+M7*1.05+M8*1.25+M9*1.25+M10*1.25+M11*1.25+M12*1.05+M13*1.25+M14*1.25+M15*1.05+M16*1.25+M17*1.05+M18*1.25+M19*1.25+M20*1.25+M21*1.05+M22*1.05+M23*1.25+M24*1.25+M25*1.25+M26*1.05+M27*1.25+M28*1.25 -> 45708.333 | ... AO32: =AO4*1+AO5*1+AO6*1.05+AO7*1.05+AO8*1.25+AO9*1.25+AO10*1.25+AO11*1.25+AO12*1.05+AO13*1.25+AO14*1.25+AO15*1.05+AO16*1.25+AO17*1.05+AO18*1.25+AO19*1.25+AO20*1.25+AO21*1.05+AO22*1.05+AO23*1.25+AO24*1.25+AO25*1.25+AO26*1.05+AO27*1.25+AO28*1.25 -> 188545.83
A33: Total Headcount | F33: =COUNTIF(F4:F28,">0") -> 3 | G33: =COUNTIF(G4:G28,">0") -> 3 | H33: =COUNTIF(H4:H28,">0") -> 3 | I33: =COUNTIF(I4:I28,">0") -> 5 | J33: =COUNTIF(J4:J28,">0") -> 5 | K33: =COUNTIF(K4:K28,">0") -> 5 | L33: =COUNTIF(L4:L28,">0") -> 5 | M33: =COUNTIF(M4:M28,">0") -> 6 | ... AO33: =COUNTIF(AO4:AO28,">0") -> 23

Sheet Operating Expenses
A1: OPERATING EXPENSES - 36-MONTH DETAIL
A3: Expense | B3: Y1M1 | C3: Y1M2 | D3: Y1M3 | E3: Y1M4 | F3: Y1M5 | G3: Y1M6 | H3: Y1M7 | I3: Y1M8 | J3: Y1M9 | K3: Y1M10 | L3: Y1M11 | M3: Y1M12 | N3: Y2M1 | O3: Y2M2 | P3: Y2M3 | Q3: Y2M4 | R3: Y2M5 | S3: Y2M6 | T3: Y2M7 | U3: Y2M8 | V3: Y2M9 | W3: Y2M10 | X3: Y2M11 | Y3: Y2M12 | Z3: Y3M1 | AA3: Y3M2 | AB3: Y3M3 | AC3: Y3M4 | AD3: Y3M5 | AE3: Y3M6 | AF3: Y3M7 | AG3: Y3M8 | AH3: Y3M9 | AI3: Y3M10 | AJ3: Y3M11 | AK3: Y3M12
A4: G&A COSTS
A5: Office Space | B5: ='Staffing Plan'!F$30*0 -> 0 | C5: ='Staffing Plan'!G$30*0 -> 0 | D5: ='Staffing Plan'!H$30*0 -> 0 | E5: ='Staffing Plan'!I$30*0 -> 0 | F5: ='Staffing Plan'!J$30*0 -> 0 | G5: ='Staffing Plan'!K$30*0 -> 0 | H5: ='Staffing Plan'!L$30*0 -> 0 | I5: ='Staffing Plan'!M$30*0 -> 0 | ... Y5: ='Staffing Plan'!AC$30*0 -> 0 | Z5: ='Staffing Plan'!AD$30*100 -> 200 | AA5: ='Staffing Plan'!AE$30*100 -> 200 | AB5: ='Staffing Plan'!AF$30*100 -> 300 | AC5: ='Staffing Plan'!AG$30*100 -> 300 | AD5: ='Staffing Plan'!AH$30*100 -> 300 | AE5: ='Staffing Plan'!AI$30*100 -> 300 | AF5: ='Staffing Plan'!AJ$30*100 -> 300 | AG5: ='Staffing Plan'!AK$30*100 -> 300 | ... AK5: ='Staffing Plan'!AO$30*100 -> 300
A6: Software/Tools | B6: ='Staffing Plan'!F$30*100 -> 0 | C6: ='Staffing Plan'!G$30*100 -> 0 | D6: ='Staffing Plan'!H$30*100 -> 0 | E6: ='Staffing Plan'!I$30*100 -> 100 | F6: ='Staffing Plan'!J$30*100 -> 100 | G6: ='Staffing Plan'!K$30*100 -> 100 | H6: ='Staffing Plan'!L$30*100 -> 100 | I6: ='Staffing Plan'!M$30*100 -> 100 | ... M6: ='Staffing Plan'!Q$30*100 -> 100 | N6: ='Staffing Plan'!R$30*125 -> 125 | O6: ='Staffing Plan'!S$30*125 -> 125 | P6: ='Staffing Plan'!T$30*125 -> 125 | Q6: ='Staffing Plan'!U$30*125 -> 250 | R6: ='Staffing Plan'!V$30*125 -> 250 | S6: ='Staffing Plan'!W$30*125 -> 250 | T6: ='Staffing Plan'!X$30*125 -> 250 | U6: ='Staffing Plan'!Y$30*125 -> 250 | ... Y6: ='Staffing Plan'!AC$30*125 -> 250 | Z6: ='Staffing Plan'!AD$30*150 -> 300 | AA6: ='Staffing Plan'!AE$30*150 -> 300 | AB6: ='Staffing Plan'!AF$30*150 -> 450 | AC6: ='Staffing Plan'!AG$30*150 -> 450 | AD6: ='Staffing Plan'!AH$30*150 -> 450 | AE6: ='Staffing Plan'!AI$30*150 -> 450 | AF6: ='Staffing Plan'!AJ$30*150 -> 450 | AG6: ='Staffing Plan'!AK$30*150 -> 450 | ... AK6: ='Staffing Plan'!AO$30*150 -> 450
A7: Travel & Entertainment | B7: 500 | C7: 500 | D7: 500 | E7: 1500 | F7: 1500 | G7: 1500 | H7: 1500 | I7: 1500 | J7: 1500 | K7: 1800 | L7: 1800 | M7: 1800 | N7: 4200 | O7: 4200 | P7: 4200 | Q7: 4800 | R7: 4800 | S7: 4800 | T7: 4800 | U7: 4800 | V7: 4800 | W7: 4800 | X7: 4800 | Y7: 4800 | Z7: 4800 | AA7: 4800 | AB7: 6000 | AC7: 6000 | AD7: 6000 | AE7: 6000 | AF7: 6000 | AG7: 6000 | AH7: 6000 | AI7: 6000 | AJ7: 6000 | AK7: 6000
A8: Professional Services | B8: 0 | C8: 0 | D8: 0 | E8: 750 | F8: 750 | G8: 750 | H8: 750 | I8: 750 | J8: 750 | K8: 750 | L8: 750 | M8: 750 | N8: 1500 | O8: 1500 | P8: 1500 | Q8: 1500 | R8: 1500 | S8: 1500 | T8: 1500 | U8: 1500 | V8: 1500 | W8: 1500 | X8: 1500 | Y8: 1500 | Z8: 2500 | AA8: 2500 | AB8: 2500 | AC8: 2500 | AD8: 2500 | AE8: 2500 | AF8: 2500 | AG8: 2500 | AH8: 2500 | AI8: 2500 | AJ8: 2500 | AK8: 2500
A9: SOC 2/Compliance | B9: 0 | C9: 0 | D9: 0 | E9: 0 | F9: 0 | G9: 0 | H9: 0 | I9: 0 | J9: 0 | K9: 4833 | L9: 4833 | M9: 4833 | N9: 833 | O9: 833 | P9: 833 | Q9: 833 | R9: 833 | S9: 8333 | T9: 8333 | U9: 833 | V9: 833 | W9: 833 | X9: 833 | Y9: 833 | Z9: 833 | AA9: 833 | AB9: 833 | AC9: 833 | AD9: 833 | AE9: 6833 | AF9: 6833 | AG9: 833 | AH9: 833 | AI9: 833 | AJ9: 833 | AK9: 833
A10: Equipment | B10: 6000 | C10: 0 | D10: 0 | E10: 2000 | F10: 0 | G10: 2000 | H10: 0 | I10: 2000 | J10: 0 | K10: 2000 | L10: 0 | M10: 0 | N10: 2000 | O10: 2000 | P10: 0 | Q10: 2000 | R10: 0 | S10: 4000 | T10: 0 | U10: 2000 | V10: 0 | W10: 0 | X10: 2000 | Y10: 4000 | Z10: 4000 | AA10: 2000 | AB10: 4000 | AC10: 0 | AD10: 0 | AE10: 2000 | AF10: 0 | AG10: 2000 | AH10: 0 | AI10: 2000 | AJ10: 0 | AK10: 2000
A11: Insurance | B11: 2500 | C11: 2500 | D11: 2500 | E11: 2500 | F11: 2500 | G11: 2500 | H11: 2500 | I11: 2500 | J11: 2500 | K11: 2500 | L11: 2500 | M11: 2500 | N11: 4000 | O11: 4000 | P11: 4000 | Q11: 4000 | R11: 4000 | S11: 4000 | T11: 4000 | U11: 4000 | V11: 4000 | W11: 4000 | X11: 4000 | Y11: 4000 | Z11: 6000 | AA11: 6000 | AB11: 6000 | AC11: 6000 | AD11: 6000 | AE11: 6000 | AF11: 6000 | AG11: 6000 | AH11: 6000 | AI11: 6000 | AJ11: 6000 | AK11: 6000
A12: Legal | B12: 0 | C12: 0 | D12: 0 | E12: 2000 | F12: 2000 | G12: 2000 | H12: 2000 | I12: 2000 | J12: 2000 | K12: 2000 | L12: 2000 | M12: 2000 | N12: 3000 | O12: 3000 | P12: 3000 | Q12: 3000 | R12: 3000 | S12: 3000 | T12: 3000 | U12: 3000 | V12: 3000 | W12: 3000 | X12: 3000 | Y12: 3000 | Z12: 4000 | AA12: 4000 | AB12: 4000 | AC12: 4000 | AD12: 4000 | AE12: 4000 | AF12: 4000 | AG12: 4000 | AH12: 4000 | AI12: 4000 | AJ12: 4000 | AK12: 4000
A13: Stipends | B13: ='Staffing Plan'!F$30*150 -> 0 | C13: ='Staffing Plan'!G$30*150 -> 0 | D13: ='Staffing Plan'!H$30*150 -> 0 | E13: ='Staffing Plan'!I$30*150 -> 150 | F13: ='Staffing Plan'!J$30*150 -> 150 | G13: ='Staffing Plan'!K$30*150 -> 150 | H13: ='Staffing Plan'!L$30*150 -> 150 | I13: ='Staffing Plan'!M$30*150 -> 150 | ... AK13: ='Staffing Plan'!AO$30*150 -> 450
A14: Miscellaneous | B14: =1500+'Staffing Plan'!F$30*50 -> 1500 | C14: =1500+'Staffing Plan'!G$30*50 -> 1500 | D14: =1500+'Staffing Plan'!H$30*50 -> 1500 | E14: =1500+'Staffing Plan'!I$30*50 -> 1550 | F14: =1500+'Staffing Plan'!J$30*50 -> 1550 | G14: =1500+'Staffing Plan'!K$30*50 -> 1550 | H14: =1500+'Staffing Plan'!L$30*50 -> 1550 | I14: =1500+'Staffing Plan'!M$30*50 -> 1550 | ... AK14: =1500+'Staffing Plan'!AO$30*50 -> 1650
A15: Total G&A | B15: =B5+B6+B7+B8+B9+B10+B11+B12+B13+B14 -> 10500 | C15: =C5+C6+C7+C8+C9+C10+C11+C12+C13+C14 -> 4500 | D15: =D5+D6+D7+D8+D9+D10+D11+D12+D13+D14 -> 4500 | E15: =E5+E6+E7+E8+E9+E10+E11+E12+E13+E14 -> 10550 | F15: =F5+F6+F7+F8+F9+F10+F11+F12+F13+F14 -> 8550 | G15: =G5+G6+G7+G8+G9+G10+G11+G12+G13+G14 -> 10550 | H15: =H5+H6+H7+H8+H9+H10+H11+H12+H13+H14 -> 8550 | I15: =I5+I6+I7+I8+I9+I10+I11+I12+I13+I14 -> 10550 | ... AK15: =AK5+AK6+AK7+AK8+AK9+AK10+AK11+AK12+AK13+AK14 -> 24183
A16: S&M COSTS
A17: Marketing Budget | B17: ='Model Inputs'!B$15 -> 5000 | C17: ='Model Inputs'!C$15 -> 5000 | D17: ='Model Inputs'!D$15 -> 5000 | E17: ='Model Inputs'!E$15 -> 10000 | F17: ='Model Inputs'!F$15 -> 10000 | G17: ='Model Inputs'!G$15 -> 10000 | H17: ='Model Inputs'!H$15 -> 10000 | I17: ='Model Inputs'!I$15 -> 10000 | ... AK17: ='Model Inputs'!AK$15 -> 20000 | AL17: ='Model Inputs'!$D$15 -> 5000 | AM17: ='Model Inputs'!$D$15 -> 5000 | AN17: ='Model Inputs'!$D$15 -> 5000
A18: SDR Commission | B18: 0 | C18: 0 | D18: 0 | E18: ='Model Inputs'!E231 -> 0 | F18: ='Model Inputs'!F231 -> 0 | G18: ='Model Inputs'!G231 -> 0 | H18: ='Model Inputs'!H231 -> 0 | I18: ='Model Inputs'!I231 -> 0 | J18: ='Model Inputs'!J231 -> 0 | K18: ='Model Inputs'!K231 -> 0 | L18: ='Model Inputs'!L231 -> 0 | ... AN18: ='Model Inputs'!AN231 -> 3750
A19: Sales Tools (CRM, etc.) | B19: 0 | C19: 0 | D19: 0 | E19: 1000 | F19: 1000 | G19: 1000 | H19: 1000 | I19: 1000 | J19: 1000 | K19: 1000 | L19: 1000 | M19: 1000 | N19: 2000 | O19: 2000 | P19: 2000 | Q19: 2000 | R19: 2000 | S19: 2000 | T19: 2000 | U19: 2000 | V19: 2000 | W19: 2000 | X19: 2000 | Y19: 2000 | Z19: 3000 | AA19: 3000 | AB19: 3000 | AC19: 3000 | AD19: 3000 | AE19: 3000 | AF19: 3000 | AG19: 3000 | AH19: 3000 | AI19: 3000 | AJ19: 3000 | AK19: 3000 | AL19: 3000 | AM19: 3000 | AN19: 3000
A20: Acquisition Spend | B20: ='Revenue Model'!B$34*'Model Inputs'!$B$20 -> 0 | C20: ='Revenue Model'!C$34*'Model Inputs'!$B$20 -> 0 | D20: ='Revenue Model'!D$34*'Model Inputs'!$B$20 -> 0 | E20: ='Revenue Model'!E$34*'Model Inputs'!$B$20 -> 0 | F20: ='Revenue Model'!F$34*'Model Inputs'!$B$20 -> 0 | G20: ='Revenue Model'!G$34*'Model Inputs'!$B$20 -> 0 | H20: ='Revenue Model'!H$34*'Model Inputs'!$B$20 -> 0 | I20: ='Revenue Model'!I$34*'Model Inputs'!$B$20 -> 0 | ... M20: ='Revenue Model'!M$34*'Model Inputs'!$B$20 -> 0 | N20: ='Revenue Model'!N$34*'Model Inputs'!$C$20 -> 0 | O20: ='Revenue Model'!O$34*'Model Inputs'!$C$20 -> 0 | P20: ='Revenue Model'!P$34*'Model Inputs'!$C$20 -> 0 | Q20: ='Revenue Model'!Q$34*'Model Inputs'!$C$20 -> 0 | R20: ='Revenue Model'!R$34*'Model Inputs'!$C$20 -> 0 | S20: ='Revenue Model'!S$34*'Model Inputs'!$C$20 -> 0 | T20: ='Revenue Model'!T$34*'Model Inputs'!$C$20 -> 0 | U20: ='Revenue Model'!U$34*'Model Inputs'!$C$20 -> 0 | ... Y20: ='Revenue Model'!Y$34*'Model Inputs'!$C$20 -> 0 | Z20: ='Revenue Model'!Z$34*'Model Inputs'!$D$20 -> 0 | AA20: ='Revenue Model'!AA$34*'Model Inputs'!$D$20 -> 0 | AB20: ='Revenue Model'!AB$34*'Model Inputs'!$D$20 -> 0 | AC20: ='Revenue Model'!AC$34*'Model Inputs'!$D$20 -> 0 | AD20: ='Revenue Model'!AD$34*'Model Inputs'!$D$20 -> 0 | AE20: ='Revenue Model'!AE$34*'Model Inputs'!$D$20 -> 0 | AF20: ='Revenue Model'!AF$34*'Model Inputs'!$D$20 -> 0 | AG20: ='Revenue Model'!AG$34*'Model Inputs'!$D$20 -> 0 | ... AL20: ='Revenue Model'!AL$34*'Model Inputs'!$D$20 -> 0 | AM20: ='Revenue Model'!AM$33*27 -> 0 | AN20: ='Revenue Model'!AN$33*27 -> 0
A21: AE + Expansion Commission | B21: =IF(1>='Model Inputs'!$B$24,'Model Inputs'!B205+'Model Inputs'!B220,0) -> 0 | C21: =IF(2>='Model Inputs'!$B$24,'Model Inputs'!C205+'Model Inputs'!C220,0) -> 0 | D21: =IF(3>='Model Inputs'!$B$24,'Model Inputs'!D205+'Model Inputs'!D220,0) -> 0 | E21: =IF(4>='Model Inputs'!$B$24,'Model Inputs'!E205+'Model Inputs'!E220,0) -> 944.30769 | F21: =IF(5>='Model Inputs'!$B$24,'Model Inputs'!F205+'Model Inputs'!F220,0) -> 1531.2 | G21: =IF(6>='Model Inputs'!$B$24,'Model Inputs'!G205+'Model Inputs'!G220,0) -> 4227.5728 | H21: =IF(7>='Model Inputs'!$B$24,'Model Inputs'!H205+'Model Inputs'!H220,0) -> 6195.8769 | I21: =IF(8>='Model Inputs'!$B$24,'Model Inputs'!I205+'Model Inputs'!I220,0) -> 6195.8769 | J21: =IF(9>='Model Inputs'!$B$24,'Model Inputs'!J205+'Model Inputs'!J220,0) -> 7724.593 | K21: =IF(10>='Model Inputs'!$B$24,'Model Inputs'!K205+'Model Inputs'!K220,0) -> 6510.6462 | L21: =IF(11>='Model Inputs'!$B$24,'Model Inputs'!L205+'Model Inputs'!L220,0) -> 6706.2769 | M21: =IF(12>='Model Inputs'!$B$24,'Model Inputs'!M205+'Model Inputs'!M220,0) -> 9845.9849 | N21: =IF(13>='Model Inputs'!$B$24,'Model Inputs'!N205+'Model Inputs'!N220,0) -> 10142.792 | O21: =IF(14>='Model Inputs'!$B$24,'Model Inputs'!O205+'Model Inputs'!O220,0) -> 10142.792 | P21: =IF(15>='Model Inputs'!$B$24,'Model Inputs'!P205+'Model Inputs'!P220,0) -> 14198.146 | Q21: =IF(16>='Model Inputs'!$B$24,'Model Inputs'!Q205+'Model Inputs'!Q220,0) -> 9771.8637 | R21: =IF(17>='Model Inputs'!$B$24,'Model Inputs'!R205+'Model Inputs'!R220,0) -> 10744.442 | S21: =IF(18>='Model Inputs'!$B$24,'Model Inputs'!S205+'Model Inputs'!S220,0) -> 22155.078 | T21: =IF(19>='Model Inputs'!$B$24,'Model Inputs'!T205+'Model Inputs'!T220,0) -> 17245.5 | U21: =IF(20>='Model Inputs'!$B$24,'Model Inputs'!U205+'Model Inputs'!U220,0) -> 17245.5 | V21: =IF(21>='Model Inputs'!$B$24,'Model Inputs'!V205+'Model Inputs'!V220,0) -> 26851.808 | W21: =IF(22>='Model Inputs'!$B$24,'Model Inputs'!W205+'Model Inputs'!W220,0) -> 15116.494 | X21: =IF(23>='Model Inputs'!$B$24,'Model Inputs'!X205+'Model Inputs'!X220,0) -> 21877.425 | Y21: =IF(24>='Model Inputs'!$B$24,'Model Inputs'!Y205+'Model Inputs'!Y220,0) -> 40132.293 | Z21: =IF(25>='Model Inputs'!$B$24,'Model Inputs'!Z205+'Model Inputs'!Z220,0) -> 32264.1 | AA21: =IF(26>='Model Inputs'!$B$24,'Model Inputs'!AA205+'Model Inputs'!AA220,0) -> 32264.1 | AB21: =IF(27>='Model Inputs'!$B$24,'Model Inputs'!AB205+'Model Inputs'!AB220,0) -> 54250.004 | AC21: =IF(28>='Model Inputs'!$B$24,'Model Inputs'!AC205+'Model Inputs'!AC220,0) -> 31595.645 | AD21: =IF(29>='Model Inputs'!$B$24,'Model Inputs'!AD205+'Model Inputs'!AD220,0) -> 33741.225 | AE21: =IF(30>='Model Inputs'!$B$24,'Model Inputs'!AE205+'Model Inputs'!AE220,0) -> 62582.449 | AF21: =IF(31>='Model Inputs'!$B$24,'Model Inputs'!AF205+'Model Inputs'!AF220,0) -> 36550.8 | AG21: =IF(32>='Model Inputs'!$B$24,'Model Inputs'!AG205+'Model Inputs'!AG220,0) -> 36550.8 | AH21: =IF(33>='Model Inputs'!$B$24,'Model Inputs'!AH205+'Model Inputs'!AH220,0) -> 71637.209 | AI21: =IF(34>='Model Inputs'!$B$24,'Model Inputs'!AI205+'Model Inputs'!AI220,0) -> 36550.8 | AJ21: =IF(35>='Model Inputs'!$B$24,'Model Inputs'!AJ205+'Model Inputs'!AJ220,0) -> 36550.8 | AK21: =IF(36>='Model Inputs'!$B$24,'Model Inputs'!AK205+'Model Inputs'!AK220,0) -> 79540.186 | AL21: =IF(37>='Model Inputs'!$B$24,'Model Inputs'!AL205+'Model Inputs'!AL220,0) -> 9137.7 | AM21: =IF(38>='Model Inputs'!$B$24,'Model Inputs'!AM205+'Model Inputs'!AM220,0) -> 9137.7 | AN21: =IF(39>='Model Inputs'!$B$24,'Model Inputs'!AN205+'Model Inputs'!AN220,0) -> 9137.7
A22: Total S&M | B22: =B$17+B$18+B$19+B$20+B$21 -> 5000 | C22: =C$17+C$18+C$19+C$20+C$21 -> 5000 | D22: =D$17+D$18+D$19+D$20+D$21 -> 5000 | E22: =E$17+E$18+E$19+E$20+E$21 -> 11944.308 | F22: =F$17+F$18+F$19+F$20+F$21 -> 12531.2 | G22: =G$17+G$18+G$19+G$20+G$21 -> 15227.573 | H22: =H$17+H$18+H$19+H$20+H$21 -> 17195.877 | I22: =I$17+I$18+I$19+I$20+I$21 -> 17195.877 | ... AN22: =AN$17+AN$18+AN$19+AN$20+AN$21 -> 20887.7
A23: OTHER OPERATING EXPENSES
A24: Loaded Payroll | B24: ='Staffing Plan'!F$32 -> 22875 | C24: ='Staffing Plan'!G$32 -> 22875 | D24: ='Staffing Plan'!H$32 -> 22875 | E24: ='Staffing Plan'!I$32 -> 38708.333 | F24: ='Staffing Plan'!J$32 -> 38708.333 | G24: ='Staffing Plan'!K$32 -> 38708.333 | H24: ='Staffing Plan'!L$32 -> 38708.333 | I24: ='Staffing Plan'!M$32 -> 45708.333 | ... AK24: ='Staffing Plan'!AO$32 -> 188545.83
A25: Product Development | B25: 30000 | C25: 30000 | D25: 30000 | E25: 30000 | F25: 30000 | G25: 30000 | H25: 30000 | I25: 30000 | J25: 30000 | K25: 30000 | L25: 30000 | M25: 30000 | N25: 50000 | O25: 50000 | P25: 50000 | Q25: 50000 | R25: 50000 | S25: 50000 | T25: 50000 | U25: 50000 | V25: 50000 | W25: 50000 | X25: 50000 | Y25: 50000 | Z25: 75000 | AA25: 75000 | AB25: 75000 | AC25: 75000 | AD25: 75000 | AE25: 75000 | AF25: 75000 | AG25: 75000 | AH25: 75000 | AI25: 75000 | AJ25: 75000 | AK25: 75000
A26: Total OpEx | B26: =B$15+B$22+B$24+B$25 -> 68375 | C26: =C$15+C$22+C$24+C$25 -> 62375 | D26: =D$15+D$22+D$24+D$25 -> 62375 | E26: =E$15+E$22+E$24+E$25 -> 91202.641 | F26: =F$15+F$22+F$24+F$25 -> 89789.533 | G26: =G$15+G$22+G$24+G$25 -> 94485.906 | H26: =H$15+H$22+H$24+H$25 -> 94454.21 | I26: =I$15+I$22+I$24+I$25 -> 103454.21 | ... AK26: =AK$15+AK$22+AK$24+AK$25 -> 395115.54 | AL26: =AL$15+AL$21+AL$23+AL$24 -> 9137.7 | AM26: =AM$15+AM$21+AM$23+AM$24 -> 9137.7 | AN26: =AN$15+AN$21+AN$23+AN$24 -> 9137.7

Sheet P&L Statement
A1: P&L STATEMENT - 36-MONTH DETAIL
A3: Line Item | B3: Y1M1 | C3: Y1M2 | D3: Y1M3 | E3: Y1M4 | F3: Y1M5 | G3: Y1M6 | H3: Y1M7 | I3: Y1M8 | J3: Y1M9 | K3: Y1M10 | L3: Y1M11 | M3: Y1M12 | N3: Y2M1 | O3: Y2M2 | P3: Y2M3 | Q3: Y2M4 | R3: Y2M5 | S3: Y2M6 | T3: Y2M7 | U3: Y2M8 | V3: Y2M9 | W3: Y2M10 | X3: Y2M11 | Y3: Y2M12 | Z3: Y3M1 | AA3: Y3M2 | AB3: Y3M3 | AC3: Y3M4 | AD3: Y3M5 | AE3: Y3M6 | AF3: Y3M7 | AG3: Y3M8 | AH3: Y3M9 | AI3: Y3M10 | AJ3: Y3M11 | AK3: Y3M12
A4: REVENUE
A5: Total Revenue (MRR) | B5: ='Revenue Model'!B$31 -> 0 | C5: ='Revenue Model'!C$31 -> 0 | D5: ='Revenue Model'!D$31 -> 0 | E5: ='Revenue Model'!E$31 -> 7150 | F5: ='Revenue Model'!F$31 -> 10709.503 | G5: ='Revenue Model'!G$31 -> 17899.835 | H5: ='Revenue Model'!H$31 -> 25452.586 | I5: ='Revenue Model'!I$31 -> 33182.414 | ... AL5: ='Revenue Model'!AL$31 -> 675903
A6: COST OF GOODS SOLD
A7: Total COGS | B7: ='COGS Analysis'!B$20 -> 0 | C7: ='COGS Analysis'!C$20 -> 0 | D7: ='COGS Analysis'!D$20 -> 0 | E7: ='COGS Analysis'!E$20 -> 3193.93 | F7: ='COGS Analysis'!F$20 -> 3943.7156 | G7: ='COGS Analysis'!G$20 -> 5122.0752 | H7: ='COGS Analysis'!H$20 -> 6526.465 | I7: ='COGS Analysis'!I$20 -> 7931.5 | ... AL7: ='COGS Analysis'!AL$20 -> 0
A8: Gross Profit | B8: =B$5-B$7 -> 0 | C8: =C$5-C$7 -> 0 | D8: =D$5-D$7 -> 0 | E8: =E$5-E$7 -> 3956.07 | F8: =F$5-F$7 -> 6765.7878 | G8: =G$5-G$7 -> 12777.76 | H8: =H$5-H$7 -> 18926.121 | I8: =I$5-I$7 -> 25250.914 | ... AK8: =AK$5-AK$7 -> 627754.69
A9: Gross Margin % | B9: =IF(B$5>0,B$8/B$5,0) -> 0 | C9: =IF(C$5>0,C$8/C$5,0) -> 0 | D9: =IF(D$5>0,D$8/D$5,0) -> 0 | E9: =IF(E$5>0,E$8/E$5,0) -> 0.5532965 | F9: =IF(F$5>0,F$8/F$5,0) -> 0.63175551 | G9: =IF(G$5>0,G$8/G$5,0) -> 0.71384791 | H9: =IF(H$5>0,H$8/H$5,0) -> 0.74358343 | I9: =IF(I$5>0,I$8/I$5,0) -> 0.76097278 | ... AK9: =IF(AK$5>0,AK$8/AK$5,0) -> 0.87615304
A10: OPERATING EXPENSES
A11: G&A | B11: ='Operating Expenses'!B$15 -> 10500 | C11: ='Operating Expenses'!C$15 -> 4500 | D11: ='Operating Expenses'!D$15 -> 4500 | E11: ='Operating Expenses'!E$15 -> 10550 | F11: ='Operating Expenses'!F$15 -> 8550 | G11: ='Operating Expenses'!G$15 -> 10550 | H11: ='Operating Expenses'!H$15 -> 8550 | I11: ='Operating Expenses'!I$15 -> 10550 | ... AK11: ='Operating Expenses'!AK$15 -> 24183
A12: Payroll (Loaded) | B12: ='Operating Expenses'!B$24 -> 22875 | C12: ='Operating Expenses'!C$24 -> 22875 | D12: ='Operating Expenses'!D$24 -> 22875 | E12: ='Operating Expenses'!E$24 -> 38708.333 | F12: ='Operating Expenses'!F$24 -> 38708.333 | G12: ='Operating Expenses'!G$24 -> 38708.333 | H12: ='Operating Expenses'!H$24 -> 38708.333 | I12: ='Operating Expenses'!I$24 -> 45708.333 | ... AK12: ='Operating Expenses'!AK$24 -> 188545.83 | AL12: ='Operating Expenses'!AL$23 -> 0 | AM12: ='Operating Expenses'!AM$23 -> 0 | AN12: ='Operating Expenses'!AN$23 -> 0 | AO12: ='Operating Expenses'!AO$23 -> 0 | AP12: ='Operating Expenses'!AP$23 -> 0 | AQ12: ='Operating Expenses'!AQ$23 -> 0 | AR12: ='Operating Expenses'!AR$23 -> 0
A13: S&M | B13: ='Operating Expenses'!B$22 -> 5000 | C13: ='Operating Expenses'!C$22 -> 5000 | D13: ='Operating Expenses'!D$22 -> 5000 | E13: ='Operating Expenses'!E$22 -> 11944.308 | F13: ='Operating Expenses'!F$22 -> 12531.2 | G13: ='Operating Expenses'!G$22 -> 15227.573 | H13: ='Operating Expenses'!H$22 -> 17195.877 | I13: ='Operating Expenses'!I$22 -> 17195.877 | ... AK13: ='Operating Expenses'!AK$22 -> 107386.71 | AL13: ='Operating Expenses'!AL$21 -> 9137.7 | AM13: ='Operating Expenses'!AM$21 -> 9137.7 | AN13: ='Operating Expenses'!AN$21 -> 9137.7 | AO13: ='Operating Expenses'!AO$21 -> 0 | AP13: ='Operating Expenses'!AP$21 -> 0 | AQ13: ='Operating Expenses'!AQ$21 -> 0 | AR13: ='Operating Expenses'!AR$21 -> 0
A14: Product Dev | B14: ='Operating Expenses'!B$25 -> 30000 | C14: ='Operating Expenses'!C$25 -> 30000 | D14: ='Operating Expenses'!D$25 -> 30000 | E14: ='Operating Expenses'!E$25 -> 30000 | F14: ='Operating Expenses'!F$25 -> 30000 | G14: ='Operating Expenses'!G$25 -> 30000 | H14: ='Operating Expenses'!H$25 -> 30000 | I14: ='Operating Expenses'!I$25 -> 30000 | ... AK14: ='Operating Expenses'!AK$25 -> 75000 | AL14: ='Operating Expenses'!AL$24 -> 0 | AM14: ='Operating Expenses'!AM$24 -> 0 | AN14: ='Operating Expenses'!AN$24 -> 0 | AO14: ='Operating Expenses'!AO$24 -> 0 | AP14: ='Operating Expenses'!AP$24 -> 0 | AQ14: ='Operating Expenses'!AQ$24 -> 0 | AR14: ='Operating Expenses'!AR$24 -> 0
A15: Total OpEx | B15: =B$11+B$12+B$13+B$14 -> 68375 | C15: =C$11+C$12+C$13+C$14 -> 62375 | D15: =D$11+D$12+D$13+D$14 -> 62375 | E15: =E$11+E$12+E$13+E$14 -> 91202.641 | F15: =F$11+F$12+F$13+F$14 -> 89789.533 | G15: =G$11+G$12+G$13+G$14 -> 94485.906 | H15: =H$11+H$12+H$13+H$14 -> 94454.21 | I15: =I$11+I$12+I$13+I$14 -> 103454.21 | ... AK15: =AK$11+AK$12+AK$13+AK$14 -> 395115.54
A16: PROFITABILITY
A17: EBITDA | B17: =B$8-B$15 -> -68375 | C17: =C$8-C$15 -> -62375 | D17: =D$8-D$15 -> -62375 | E17: =E$8-E$15 -> -87246.571 | F17: =F$8-F$15 -> -83023.745 | G17: =G$8-G$15 -> -81708.146 | H17: =H$8-H$15 -> -75528.089 | I17: =I$8-I$15 -> -78203.297 | ... AK17: =AK$8-AK$15 -> 232639.15
A18: EBITDA Margin % | B18: =IF(B$5>0,B$17/B$5,0) -> 0 | C18: =IF(C$5>0,C$17/C$5,0) -> 0 | D18: =IF(D$5>0,D$17/D$5,0) -> 0 | E18: =IF(E$5>0,E$17/E$5,0) -> -12.202318 | F18: =IF(F$5>0,F$17/F$5,0) -> -7.7523431 | G18: =IF(G$5>0,G$17/G$5,0) -> -4.564743 | H18: =IF(H$5>0,H$17/H$5,0) -> -2.9674033 | I18: =IF(I$5>0,I$17/I$5,0) -> -2.3567694 | ... AK18: =IF(AK$5>0,AK$17/AK$5,0) -> 0.32469291
A20: Cumulative EBITDA | B20: =B17 -> -68375 | C20: =B20+C17 -> -130750 | D20: =C20+D17 -> -193125 | E20: =D20+E17 -> -280371.57 | F20: =E20+F17 -> -363395.32 | G20: =F20+G17 -> -445103.46 | H20: =G20+H17 -> -520631.55 | I20: =H20+I17 -> -598834.85 | J20: =I20+J17 -> -669846.63 | ... AK20: =AJ20+AK17 -> -233385.05
A21: Cash Position | B21: ='Model Inputs'!$B$83+B20 -> 2431625 | C21: ='Model Inputs'!$B$83+C20 -> 2369250 | D21: ='Model Inputs'!$B$83+D20 -> 2306875 | E21: ='Model Inputs'!$B$83+E20 -> 2219628.4 | F21: ='Model Inputs'!$B$83+F20 -> 2136604.7 | G21: ='Model Inputs'!$B$83+G20 -> 2054896.5 | H21: ='Model Inputs'!$B$83+H20 -> 1979368.4 | I21: ='Model Inputs'!$B$83+I20 -> 1901165.2 | ... AK21: ='Model Inputs'!$B$83+AK20 -> 2266615
A22: Runway (Months) | B22: =COUNTIF(B21:AK21,">0") -> 36

Sheet Unit Economics
A1: UNIT ECONOMICS
A3: Metric | B3: Formula | C3: Year 1 | D3: Year 2 | E3: Year 3 | F3: Benchmark
A4: REVENUE PER SEAT
A5: Revenue per Active Seat | B5: =IF('Revenue Model'!B$27>0,'Revenue Model'!B$30/'Revenue Model'!B$27,0) -> 0 | C5: =IF('Revenue Model'!C$27>0,'Revenue Model'!C$30/'Revenue Model'!C$27,0) -> 0 | D5: =IF('Revenue Model'!D$27>0,'Revenue Model'!D$30/'Revenue Model'!D$27,0) -> 0 | E5: =IF('Revenue Model'!E$27>0,'Revenue Model'!E$30/'Revenue Model'!E$27,0) -> 0.12208866 | F5: =IF('Revenue Model'!F$27>0,'Revenue Model'!F$30/'Revenue Model'!F$27,0) -> 0.19134364 | G5: =IF('Revenue Model'!G$27>0,'Revenue Model'!G$30/'Revenue Model'!G$27,0) -> 0.13639424 | H5: =IF('Revenue Model'!H$27>0,'Revenue Model'!H$30/'Revenue Model'!H$27,0) -> 0.1104924 | I5: =IF('Revenue Model'!I$27>0,'Revenue Model'!I$30/'Revenue Model'!I$27,0) -> 0.1104924 | ... AK5: =IF('Revenue Model'!AK$27>0,'Revenue Model'!AK$30/'Revenue Model'!AK$27,0) -> 0.020414326
A6: VARIABLE COGS (Per Seat/Month)
A7: Storage | B7: GB x Rate | C7: ='Model Inputs'!$B$60 -> 3.4 | D7: ='Model Inputs'!$C$60 -> 2.7 | E7: ='Model Inputs'!$D$60 -> 2.08 | F7: Filebase enterprise
A8: Bandwidth | B8: Cache-adjusted | C8: ='Model Inputs'!$B$61 -> 0.72 | D8: ='Model Inputs'!$C$61 -> 0.47 | E8: ='Model Inputs'!$D$61 -> 0.31 | F8: CDN optimized
A9: Compute | B9: Lambda/API | C9: ='Model Inputs'!$B$62 -> 0.12 | D9: ='Model Inputs'!$C$62 -> 0.08 | E9: ='Model Inputs'!$D$62 -> 0.06 | F9: Pay-per-use
A10: Data Replication | B10: S3 cross-region | C10: ='Model Inputs'!$B$63 -> 0.24 | D10: ='Model Inputs'!$C$63 -> 0.18 | E10: ='Model Inputs'!$D$63 -> 0.14 | F10: DR costs
A11: Support Automation | B11: Intercom (Audited) | C11: ='Model Inputs'!$B$64 -> 0 | D11: ='Model Inputs'!$C$64 -> 0.06 | E11: ='Model Inputs'!$D$64 -> 0.04 | F11: Y1: 100% off
A12: Payment Processing | B12: 2.9% x Revenue | C12: =C5*'Model Inputs'!$B$65 -> 0 | D12: =D5*'Model Inputs'!$C$65 -> 0 | E12: =E5*'Model Inputs'!$D$65 -> 0.003540571 | F12: Stripe standard
A13: Total Variable COGS | B13: Sum of above | C13: =SUM(C7:C12) -> 4.48 | D13: =SUM(D7:D12) -> 3.49 | E13: =SUM(E7:E12) -> 2.6335406 | F13: Scales linearly
A14: FIXED INFRASTRUCTURE
A15: Monthly Fixed Costs | B15: Platform+Infra | C15: {=AVERAGE('COGS Analysis'!B12:M12+'COGS Analysis'!B13:M13+'COGS Analysis'!B14:M14+'COGS Analysis'!B16:M16+'COGS Analysis'!B17:M17)} -> 1125 | D15: {=AVERAGE('COGS Analysis'!N12:Y12+'COGS Analysis'!N13:Y13+'COGS Analysis'!N14:Y14+'COGS Analysis'!N16:Y16+'COGS Analysis'!N17:Y17)} -> 3236.75 | E15: {=AVERAGE('COGS Analysis'!Z12:AK12+'COGS Analysis'!Z13:AK13+'COGS Analysis'!Z14:AK14+'COGS Analysis'!Z16:AK16+'COGS Analysis'!Z17:AK17)} -> 5589 | F15: Step function
A16: Avg Seats | B16: ='Revenue Model'!B$27 -> 0 | C16: ='Revenue Model'!C$27 -> 0 | D16: ='Revenue Model'!D$27 -> 0 | E16: ='Revenue Model'!E$27 -> 242 | F16: ='Revenue Model'!F$27 -> 145 | G16: ='Revenue Model'!G$27 -> 218 | H16: ='Revenue Model'!H$27 -> 266 | I16: ='Revenue Model'!I$27 -> 266 | ... AK16: ='Revenue Model'!AK$27 -> 1505
A17: Fixed COGS per Seat | B17: Fixed / Seats | C17: =IF(C16>0,C15/C16,0) -> 0 | D17: =IF(D16>0,D15/D16,0) -> 0 | E17: =IF(E16>0,E15/E16,0) -> 23.095041 | F17: Decreases with scale
A18: GROSS PROFIT ANALYSIS
A19: Total COGS per Seat | B19: Variable + Fixed | C19: =C13+C17 -> 4.48 | D19: =D13+D17 -> 3.49 | E19: =E13+E17 -> 25.728582 | F19: All-in cost
A20: Gross Profit per Seat/Mo | B20: Revenue - COGS | C20: =C5-C19 -> -4.48 | D20: =D5-D19 -> -3.49 | E20: =E5-E19 -> -25.606493 | F20: Higher = better
A21: Gross Margin % | B21: (GP / Rev) x 100 | C21: =IF(C5>0,C20/C5,0) -> 0 | D21: =IF(D5>0,D20/D5,0) -> 0 | E21: =IF(E5>0,E20/E5,0) -> -209.73688 | F21: 75-87% achieved
A22: LIFETIME VALUE
A23: Seats per Account | B23: =IF('Revenue Model'!B$34>0,'Revenue Model'!B$27/'Revenue Model'!B$34,0) -> 0 | C23: =IF('Revenue Model'!C$34>0,'Revenue Model'!C$27/'Revenue Model'!C$34,0) -> 0 | D23: =IF('Revenue Model'!D$34>0,'Revenue Model'!D$27/'Revenue Model'!D$34,0) -> 0 | E23: =IF('Revenue Model'!E$34>0,'Revenue Model'!E$27/'Revenue Model'!E$34,0) -> 7.8064516 | F23: =IF('Revenue Model'!F$34>0,'Revenue Model'!F$27/'Revenue Model'!F$34,0) -> 8.0555556 | G23: =IF('Revenue Model'!G$34>0,'Revenue Model'!G$27/'Revenue Model'!G$34,0) -> 8.72 | H23: =IF('Revenue Model'!H$34>0,'Revenue Model'!H$27/'Revenue Model'!H$34,0) -> 9.1724138 | I23: =IF('Revenue Model'!I$34>0,'Revenue Model'!I$27/'Revenue Model'!I$34,0) -> 9.5 | ... AK23: =IF('Revenue Model'!AK$34>0,'Revenue Model'!AK$27/'Revenue Model'!AK$34,0) -> 27.87037
A24: CAC (per Account) | B24: All-in | C24: =IF(SUM('Revenue Model'!B33:M33)>0,SUM('Operating Expenses'!B22:M22)/SUM('Revenue Model'!B33:M33),0) -> 0 | D24: =IF(SUM('Revenue Model'!N33:Y33)>0,SUM('Operating Expenses'!N22:Y22)/SUM('Revenue Model'!N33:Y33),0) -> 0 | E24: =IF(SUM('Revenue Model'!Z33:AK33)>0,SUM('Operating Expenses'!Z22:AK22)/SUM('Revenue Model'!Z33:AK33),0) -> 0 | F24: $200-300 PLG
A25: Monthly GP per Account | B25: GP/seat x seats | C25: =C20*C23 -> 0 | D25: =D20*D23 -> 0 | E25: =E20*E23 -> -199.89585 | F25: Account-level GP
A26: Avg Customer Lifetime (mo) | B26: 1/Churn (capped 60) | C26: =MIN(1/'Model Inputs'!$B$53,60) -> 60 | D26: =MIN(1/'Model Inputs'!$C$53,60) -> 57.142857 | E26: =MIN(1/'Model Inputs'!$D$53,60) -> 60 | F26: Derived from churn
A27: LTV (per Account) | B27: GP x Lifetime | C27: =C25*C26 -> 0 | D27: =D25*D26 -> 0 | E27: =E25*E26 -> -11993.751 | F27: >$1,000
A28: LTV:CAC Ratio | B28: LTV / CAC | C28: =IF(C24>0,C27/C24,0) -> 0 | D28: =IF(D24>0,D27/D24,0) -> 0 | E28: =IF(E24>0,E27/E24,0) -> 0 | F28: >3x
A29: CAC Payback (months) | B29: CAC / Monthly GP | C29: =IF(C25>0,C24/C25,0) -> 0 | D29: =IF(D25>0,D24/D25,0) -> 0 | E29: =IF(E25>0,E24/E25,0) -> 0 | F29: <18 months

Sheet Cap Table & SAFE
A1: CAPITALIZATION TABLE - $2.5M TIERED SAFE
A3: Shareholder | B3: Pre-Money % | C3: Post-Conversion % | D3: Notes
A4: Founders (Common) | B4: 0.9872 | C4: 0.8459 | D4: Founding shares
A5: Pre-Seed Angels | B5: 0.0128 | C5: 0.011 | D5: Prior investment
A6: Pre-SAFE Total | B6: 1 | C6: =C4+C5 -> 0.8569 | D6: -
A7: Tier 1 SAFE ($1M @ $16M) | B7: - | C7: 0.0625 | D7: Best terms - early believers
A8: Tier 2 SAFE ($1M @ $18M) | B8: - | C8: 0.0556 | D8: Standard terms
A9: Tier 3 SAFE ($0.5M @ $20M) | B9: - | C9: 0.025 | D9: Limited allocation
A10: Total SAFE Investors | B10: - | C10: 0.1431 | D10: Blended ownership
A13: TIERED SAFE STRUCTURE
A14: Tier
A15: Tier 1 | B15: 1000000 | C15: 16000000 | D15: 0.0625 | E15: Best terms - early believers
A16: Tier 2 | B16: 1000000 | C16: 18000000 | D16: 0.0556 | E16: Standard terms
A17: Tier 3 | B17: 500000 | C17: 20000000 | D17: 0.025 | E17: Limited allocation
A18: TOTAL | B18: 2500000 | C18: $17.14M blended | D18: 0.1431 | E18: -

Sheet Use of Funds
A1: USE OF FUNDS - $2.5M TIERED SAFE
A3: Category | B3: Amount | C3: % | D3: Key Investments
A4: Team Building | B4: 600000 | C4: 0.24 | D4: 7 FTEs Y1 - Founder-led
A5: Sales & Marketing | B5: 500000 | C5: 0.2 | D5: PLG funnel, content
A6: Product & Infra | B6: 400000 | C6: 0.16 | D6: Security, ZK-proofs, Solana
A7: G&A / Operations | B7: 250000 | C7: 0.1 | D7: Fractional CFO, remote ops
A8: Working Capital | B8: 750000 | C8: 0.3 | D8: Extended runway buffer
A9: Total | B9: 2500000 | C9: 1 | D9: ~28-month runway
A12: MILESTONE SCHEDULE
A13: Period | B13: Milestones | C13: HC | D13: Burn
A14: Q1 (M1-M3) | B14: MVP Build | C14: 3 | D14: ~$65K
A15: Q2 (M4-M6) | B15: Beta Launch | C15: 4 | D15: ~$70K
A16: Q3 (M7-M9) | B16: Security Hardening | C16: 6 | D16: ~$75K
A17: Q4 (M10-M12) | B17: GTM Validation | C17: 7 | D17: ~$85K
A18: Y1 End | B18: ~$1.7M ARR Target | C18: 7 | D18: Avg ~$75K

Sheet Model Inputs
A1: BLOCKDRIVE FINANCIAL MODEL - TRUE INPUTS
A3: PRICING TIERS (List Prices)
A4: Tier | B4: $/Month | C4: Unit | D4: Min Seats | E4: Notes
A5: Pro | B5: 9 | C5: flat | D5: 1 | E5: Privacy individuals, 200GB
A6: Power User | B6: 49 | C6: flat | D6: 1 | E6: Creatives, 2TB + unmetered transfer
A7: Scale | B7: 29 | C7: per seat | D7: 2 | E7: SMB/boutique, 2-seat min wedge strategy
A8: Mid-Market | B8: 39 | C8: per seat | D8: 50 | E8: 50-99 seats, SSO/Invoicing/Audit
A9: Enterprise | B9: 49 | C9: per seat | D9: 100 | E9: 100+ seats, white glove, SLA
A11: TRAFFIC & MARKETING
A12: Parameter | B12: Year 1 | C12: Year 2 | D12: Year 3 | E12: Notes
A13: M4 Launch Traffic | B13: 15000 | C13: - | D13: - | E13: Base Case: PH + HN + 3mo founder hustle
A14: Traffic MoM Growth % | B14: 0.15 | C14: 0.08 | D14: 0.05 | E14: Base organic growth (steps up with budget)
A15: Monthly Marketing Budget (Calculated) | B15: =$B$25+(B169+B171+B173)*$B$26 -> 5000 | C15: =$B$25+(C169+C171+C173)*$B$26 -> 5000 | D15: =$B$25+(D169+D171+D173)*$B$26 -> 5000 | E15: =$B$25+(E169+E171+E173)*$B$26 -> 10000 | F15: =$B$25+(F169+F171+F173)*$B$26 -> 10000 | G15: =$B$25+(G169+G171+G173)*$B$26 -> 10000 | H15: =$B$25+(H169+H171+H173)*$B$26 -> 10000 | I15: =$B$25+(I169+I171+I173)*$B$26 -> 10000 | ... AK15: =$B$25+(AK169+AK171+AK173)*$B$26 -> 20000
A16: Visit-to-Signup Rate | B16: 0.03 | C16: 0.035 | D16: 0.04 | E16: Improves with brand/UX
A17: Signup-to-Trial Rate | B17: 0.25 | C17: 0.3 | D17: 0.35 | E17: Lead to trial conversion
A18: Trial-to-Paid Rate | B18: 0.52 | C18: 0.58 | D18: 0.65 | E18: CC-required, opt-out model
A19: PLG Seats (10% of Sales) | B19: =ROUND('Revenue Model'!B16*$E$50,0) -> 0 | C19: =ROUND('Revenue Model'!C16*$E$50,0) -> 0 | D19: =ROUND('Revenue Model'!D16*$E$50,0) -> 0 | E19: =ROUND('Revenue Model'!E16*$E$50,0) -> 22 | F19: =ROUND('Revenue Model'!F16*$E$50,0) -> 13 | G19: =ROUND('Revenue Model'!G16*$E$50,0) -> 20 | H19: =ROUND('Revenue Model'!H16*$E$50,0) -> 24 | I19: =ROUND('Revenue Model'!I16*$E$50,0) -> 24 | ... AL19: =ROUND('Revenue Model'!AL16*$E$50,0) -> 0
A20: PLG Accounts (derived) | B20: =IF(B121>0,ROUND(B19/B121,0),0) -> 0 | C20: =IF(C121>0,ROUND(C19/C121,0),0) -> 0 | D20: =IF(D121>0,ROUND(D19/D121,0),0) -> 0 | E20: =IF(E121>0,ROUND(E19/E121,0),0) -> 22 | F20: =IF(F121>0,ROUND(F19/F121,0),0) -> 12 | G20: =IF(G121>0,ROUND(G19/G121,0),0) -> 17 | H20: =IF(H121>0,ROUND(H19/H121,0),0) -> 19 | I20: =IF(I121>0,ROUND(I19/I121,0),0) -> 18 | ... AL20: =IF(AL121>0,ROUND(AL19/AL121,0),0) -> 0
A21: Sales Commission Rate | B21: 0.1 | E21: 10% of first-year ACV
A22: AE Monthly Draw (Guarantee) | B22: 5000 | E22: Fixed base for SDR function
A23: AE Draw Period (months) | B23: 3 | E23: When SDR function begins
A24: Commission Start Month | B24: 4 | C24: 1 | D24: 1 | E24: When sales commissions begin
A25: Base Marketing Budget | B25: 5000
A26: Per-AE Marketing Budget | B26: 5000
A27: PLG CHANNEL MIX
A28: Tier Distribution | B28: % of PLG | C28: Avg Seats | D28: List $/Seat | E28: Notes
A29: Pro | B29: 0.45 | C29: 1 | D29: =$B$5 -> 9 | E29: Individual privacy users
A30: Power User | B30: 0.35 | C30: 1 | D30: =$B$6 -> 49 | E30: Creatives, high-volume
A31: Scale (2-seat) | B31: 0.15 | C31: 2 | D31: =$B$7 -> 29 | E31: Co-founder pairs, micro teams
A32: Scale (5-seat) | B32: 0.05 | C32: 5 | D32: =$B$7 -> 29 | E32: Small teams self-serve
A33: Total PLG | B33: =SUM(B29:B32) -> 1 | C33: =SUMPRODUCT(B29:B32,C29:C32) -> 1.35 | E33: Weighted avg seats/account
A35: LAUNCH WAITLIST
A36: PLG Waitlist Size | B36: 75 | C36: Avg Seats | D36: List $/Seat | E36: Notes
A37: Waitlist Conversion Rate | B37: 0.25 | C37: Waitlist Conversions | D37: =B36*B37 -> 18.75 | E37: Small team sales
A38: Scale (15-seat) | B38: 0.55 | C38: 15 | D38: =$B$7 -> 29 | E38: Core SMB segment
A39: Scale (25-seat) | B39: 0.35 | C39: 25 | D39: =$B$7 -> 29 | E39: Larger SMB deals
A40: Total Sales | B40: =SUM(B37:B39) -> 1.15 | C40: =SUMPRODUCT(B37:B39,C37:C39) -> 17 | E40: Weighted avg seats/deal
A41: Monthly Referral Rate | B41: =IF(1<=12,$C$127,IF(1<=24,$E$127,$G$127)) -> 0.004 | C41: =IF(2<=12,$C$127,IF(2<=24,$E$127,$G$127)) -> 0.004 | D41: =IF(3<=12,$C$127,IF(3<=24,$E$127,$G$127)) -> 0.004 | E41: =IF(4<=12,$C$127,IF(4<=24,$E$127,$G$127)) -> 0.004 | F41: =IF(5<=12,$C$127,IF(5<=24,$E$127,$G$127)) -> 0.004 | G41: =IF(6<=12,$C$127,IF(6<=24,$E$127,$G$127)) -> 0.004 | H41: =IF(7<=12,$C$127,IF(7<=24,$E$127,$G$127)) -> 0.004 | I41: =IF(8<=12,$C$127,IF(8<=24,$E$127,$G$127)) -> 0.004 | J41: =IF(9<=12,$C$127,IF(9<=24,$E$127,$G$127)) -> 0.004 | K41: =IF(10<=12,$C$127,IF(10<=24,$E$127,$G$127)) -> 0.004 | L41: =IF(11<=12,$C$127,IF(11<=24,$E$127,$G$127)) -> 0.004 | M41: =IF(12<=12,$C$127,IF(12<=24,$E$127,$G$127)) -> 0.004 | N41: =IF(13<=12,$C$127,IF(13<=24,$E$127,$G$127)) -> 0.006 | O41: =IF(14<=12,$C$127,IF(14<=24,$E$127,$G$127)) -> 0.006 | P41: =IF(15<=12,$C$127,IF(15<=24,$E$127,$G$127)) -> 0.006 | Q41: =IF(16<=12,$C$127,IF(16<=24,$E$127,$G$127)) -> 0.006 | R41: =IF(17<=12,$C$127,IF(17<=24,$E$127,$G$127)) -> 0.006 | S41: =IF(18<=12,$C$127,IF(18<=24,$E$127,$G$127)) -> 0.006 | T41: =IF(19<=12,$C$127,IF(19<=24,$E$127,$G$127)) -> 0.006 | U41: =IF(20<=12,$C$127,IF(20<=24,$E$127,$G$127)) -> 0.006 | V41: =IF(21<=12,$C$127,IF(21<=24,$E$127,$G$127)) -> 0.006 | W41: =IF(22<=12,$C$127,IF(22<=24,$E$127,$G$127)) -> 0.006 | X41: =IF(23<=12,$C$127,IF(23<=24,$E$127,$G$127)) -> 0.006 | Y41: =IF(24<=12,$C$127,IF(24<=24,$E$127,$G$127)) -> 0.006 | Z41: =IF(25<=12,$C$127,IF(25<=24,$E$127,$G$127)) -> 0.008 | AA41: =IF(26<=12,$C$127,IF(26<=24,$E$127,$G$127)) -> 0.008 | AB41: =IF(27<=12,$C$127,IF(27<=24,$E$127,$G$127)) -> 0.008 | AC41: =IF(28<=12,$C$127,IF(28<=24,$E$127,$G$127)) -> 0.008 | AD41: =IF(29<=12,$C$127,IF(29<=24,$E$127,$G$127)) -> 0.008 | AE41: =IF(30<=12,$C$127,IF(30<=24,$E$127,$G$127)) -> 0.008 | AF41: =IF(31<=12,$C$127,IF(31<=24,$E$127,$G$127)) -> 0.008 | AG41: =IF(32<=12,$C$127,IF(32<=24,$E$127,$G$127)) -> 0.008 | AH41: =IF(33<=12,$C$127,IF(33<=24,$E$127,$G$127)) -> 0.008 | AI41: =IF(34<=12,$C$127,IF(34<=24,$E$127,$G$127)) -> 0.008 | AJ41: =IF(35<=12,$C$127,IF(35<=24,$E$127,$G$127)) -> 0.008 | AK41: =IF(36<=12,$C$127,IF(36<=24,$E$127,$G$127)) -> 0.008 | AL41: =IF(37<=12,$C$127,IF(37<=24,$E$127,$G$127)) -> 0.008
A42: SALES CAPACITY
A43: PRE-LAUNCH PIPELINE | C43: Year 2 | D43: Year 3 | E43: Notes
A44: Pipeline Deals at Launch | B44: 8 | C44: Pipeline Close Rate | D44: 0.75 | E44: Pipeline Conversions | F44: =B44*D44 -> 6
A45: Founder Deals/Month | B45: 5 | C45: 4 | D45: 0 | E45: Ramps down as team scales
A46: AE Deals/Month (each) | B46: 8 | C46: 8 | D46: 8 | E46: Top-tier AE (8/mo = ~$1.9M quota at $20K ACV)
A47: AE1 Start Month | B47: 4 | C47: - | D47: - | E47: From Staffing Plan
A48: AE2 Start Month | B48: 16 | C48: 16 | D48: - | E48: From Staffing Plan
A49: AE3 Start Month | B49: 22 | C49: 22 | D49: 27 | E49: From Staffing Plan
A50: AE Ramp Period (months) | B50: 4 | D50: PLG Seat % | E50: 0.1 | F50: PLG Seats Base | G50: 1 | H50: PLG Seats Growth | I50: 0.08 | J50: PLG Seats Cap | K50: 5
A51: SDR COMMISSION
A52: SDR Meeting Bonus ($) | B52: 125 | C52: Year 2 | D52: Year 3 | E52: Notes
A53: SDR Closed-Won Rate (%) | B53: 0.015 | C53: 0.0175 | D53: 0.015 | E53: PLG-dominant, improves with enterprise mix
A54: Meetings per SDR/Month | B54: 15 | C54: 0.15 | D54: 0.2 | E54: % of new accounts from referrals
A55: Execution Rate | B55: 0.7 | E55: Discounts + billing friction buffer
B56: 0.01 | C56: 2.5 | D56: 3 | E56: Referred accounts tend to be similar
B57: 0.85
A58: VARIABLE COGS (Per Seat/Month)
A59: Parameter | B59: Year 1 | C59: Year 2 | D59: Year 3 | E59: Notes
A60: Storage | B60: 3.4 | C60: 2.7 | D60: 2.08 | E60: Filebase volume pricing
A61: Bandwidth | B61: 0.72 | C61: 0.47 | D61: 0.31 | E61: CDN + Egress
A62: Compute | B62: 0.12 | C62: 0.08 | D62: 0.06 | E62: Lambda/API variable
A63: Data Replication | B63: 0.24 | C63: 0.18 | D63: 0.14 | E63: Per-seat DR costs
A64: Support Automation | B64: 0 | C64: 0.06 | D64: 0.04 | E64: Intercom Early Stage
A65: Payment Processing % | B65: 0.029 | C65: 0.029 | D65: 0.029 | E65: Stripe 2.9%
A66: Blockchain Gas (SOL) | B66: 0.01 | C66: 0.008 | D66: 0.006
A67: STEP-FUNCTION COSTS (Monthly)
A68: Parameter | B68: Year 1 | C68: Year 2 | D68: Year 3 | E68: Notes
A69: Filebase Platform | B69: 1500 | C69: 3000 | D69: 5000 | E69: Enterprise tiers
A70: Blockchain RPC (Alchemy/Helius) | B70: 0 | C70: 249 | D70: 499 | E70: Solana RPC
A71: Monitoring (DataDog) | B71: 0 | C71: 350 | D71: 600 | E71: APM @ $31/host
E72: Paid acquisition, SEO, email
A73: Transactional Email (SendGrid) | B73: 0 | C73: 50 | D73: 90
A74: FIXED COSTS (Monthly)
A75: Parameter | B75: Year 1 | C75: Year 2 | D75: Year 3 | E75: Notes
A76: Base Compute | B76: 200 | C76: 350 | D76: 500 | E76: Always-on servers
A77: DR Base Infrastructure | B77: 200 | C77: 300 | D77: 400 | E77: Disaster recovery
A78: Fractional Legal | B78: 7500 | C78: 7500 | D78: 10000 | E78: ToS, DPA, compliance
A79: Product Dev Budget | B79: 30000 | C79: 50000 | D79: 75000 | E79: Tools, infra, R&D
A80: Stipend per Person | B80: 150 | C80: 150 | D80: 150 | E80: Remote work allowance
A81: FUNDING & CASH
A82: Parameter | B82: Value
A83: Seed Funding Amount | B83: 2500000 | C83: Y2 Value | D83: Source
A84: Crypto/Web3 - Addressable Pool | B84: 25000 | C84: 25000 | D84: US subset of 59K global
A85: Crypto/Web3 - Reachable % | B85: 0.15 | C85: 0.2 | D85: Community penetration
A86: Crypto/Web3 - Reachable Universe | B86: =B84*B85 -> 3750 | C86: =C84*C85 -> 5000 | D86: Pool × reach %
A87: Crypto/Web3 - Conversion % | B87: 0.04 | C87: 0.05 | D87: Ideological alignment
A88: Crypto/Web3 - Max Accounts | B88: =B86*B87 -> 150 | C88: =C86*C87 -> 250 | D88: Universe × conv %
A89: Crypto/Web3 - Y1 Target (67%) | B89: =ROUND(B88*0.67,0) -> 101 | C89: 235 | D89: Conservative execution
A91: Crypto Law - Addressable Pool | B91: 400 | C91: 400 | D91: Miami/NY/SF/Austin hubs
A92: Crypto Law - Reachable % | B92: 0.25 | C92: 0.4 | D92: Tight community
A93: Crypto Law - Reachable Universe | B93: =B91*B92 -> 100 | C93: =C91*C92 -> 160 | D93: Pool × reach %
A94: Crypto Law - Conversion % | B94: 0.08 | C94: 0.1 | D94: Privilege pain point
A95: Crypto Law - Max Accounts | B95: =ROUND(B93*B94,0) -> 8 | C95: =ROUND(C93*C94,0) -> 16 | D95: Universe × conv %
A97: Healthcare - Max Accounts (Y2+) | B97: 0 | C97: 20 | D97: HIPAA-conscious niche
A98: Family Offices - Max Accounts (Y2+) | B98: 0 | C98: 10 | D98: Privacy value prop
A99: General Legal - Max Accounts (Y2+) | B99: 0 | C99: 13 | D99: Non-crypto expansion
A100: FinTech - Max Accounts (Y2+) | B100: 0 | C100: 25 | D100: SOC 2 Type II enables (Q1 Y2)
A101: SOC 2 Type I | B101: Y2M1 | C101: Basic security controls | D101: Required for compliance-sensitive verticals
A102: SOC 2 Type II | B102: Y2M1 | C102: Enables FinTech & enterprise sales
A103: HIPAA | B103: Y2M1 | C103: Enables Healthcare vertical | D103: Target ACV | E103: Implied Seats
A104: Crypto/Web3 Companies | B104: 4000 | C104: 8000 | D104: 6000 | E104: =ROUND(D104/274,0) -> 22
A105: Crypto Law Firms | B105: 8000 | C105: 15000 | D105: 12000 | E105: =ROUND(D105/274,0) -> 44
...
